result/10_20260629_075914/testbench/common/mem.v
`timescale 1ns/1ps

module ram # 
(parameter DATA_WIDTH = 64, ADDR_WIDTH = 16) //default is: 64b/word * (2^16)address) = 4Mb
(
clk         , // Clock Input
address     , // Address Input
d           , // Data input
q           , // Data output
cs          , // Chip Select
web           // Write Enable/Read Enable, low active
); 

localparam RAM_DEPTH = 1 << ADDR_WIDTH;

//--------------Input Ports----------------------- 
input clk;
input [ADDR_WIDTH-1:0] address;
input cs;
input web;

//--------------Inout Ports----------------------- 
input [DATA_WIDTH-1:0]  d;
output [DATA_WIDTH-1:0]  q;
reg [DATA_WIDTH-1:0]  data_out;

//--------------Internal variables---------------- 
reg [DATA_WIDTH-1:0] mem [0:RAM_DEPTH-1];

//--------------Core Function--------------------- 
// Tri-State Buffer control 
// output : When web = 1, oe = 1, cs = 1
assign q = (cs) ? data_out : 'bz; 

// Memory Write Block 
// Write Operation : When web = 0, cs = 1
always @ (posedge clk)
begin : MEM_WRITE
   if ( cs && ~web ) begin
       mem[address] = d;
   end
end

// Memory Read Block 
// Read Operation : When web = 1, oe = 1, cs = 1
always @ (address or cs or web)
begin : MEM_READ
    if (cs && web ) begin
         data_out = mem[address];
    end
end

endmodule

lab8/lab8_framework/lab8_framework/accelerator.v

module accelerator (
    clk, comp_enb, 
    mem_addr, mem_data, 
    mem_read_enb, mem_write_enb, 
    res_addr, res_data, 
    busyb, done
);

    input clk;
    input comp_enb;
    output reg [3:0] mem_addr;
    input [63:0] mem_data;
    output reg mem_read_enb;
    output reg mem_write_enb;
    output reg [3:0] res_addr;
    output reg [63:0] res_data;
    output reg busyb;
    output reg done;

    
    // Declare states
	parameter S_RST = 0, S_READ = 1, S_WORK = 2, S_DONE = 3;
	reg [1:0] state;
    reg [1:0] counter;
    reg [63:0] reg1, reg2;
	// Determine the next state synchronously, based on the
	// current state and the input
	always @ (posedge clk) begin
		if (comp_enb) begin
			state <= S_RST;
            res_addr <= 0;
            res_data <= 0;
            reg1 <= 0;
            reg2 <= 0;
            counter <= 0;
            mem_read_enb <= 0;
            mem_write_enb <= 1;
		end
		else
		begin
			case (state)
				S_RST: begin
                    if(~comp_enb)
                        state <= S_READ;
                end
				S_READ: begin
                    if(counter == 2'd0) begin
                        mem_addr <= 4'd0;
                        counter <= counter + 1;
                    end 
                    else if (counter == 2'd1) begin
                        reg1 <= mem_data;
                        mem_addr <= 4'd1;
                        counter <= counter + 1;
                    end
                    else if (counter == 2'd2) begin
                        reg2 <= mem_data;
                        counter <= 0;
                        state <= S_WORK;
                    end
                end
                S_WORK: begin
                    if(counter==0) begin
                        mem_write_enb <= 0;
                        res_addr = 4'd2;
                        res_data = reg1 + reg2;
                        counter <= counter + 1;
                    end
                    else begin
                        mem_write_enb <= 1;
                        counter <= 0;
                        state <= S_DONE;
                    end
                end
                default: begin //S_DONE
                    if(comp_enb)
                        state <= S_RST;
                end
			endcase
	    end
    end
	
	// Determine the output based only on the current state
	// and the input (do not wait for a clock edge).
	always @ (state)
	begin
		case (state)
			S_WORK: begin
                busyb <= 0;
                done <= 0;
            end
            S_DONE: begin
                busyb <= 0;
                done <= 1;
            end
            default: begin //S_RST
                busyb <= 1;
                done <= 0;
            end
		endcase
	end

endmodule

lab8/lab8_flow_fast/lab8_flow_fast/testbench_top.v

// `timescale 1ns/1ns
`include "mem.v"
`include "accelerator.v"
`define T 2 // define macro for clock period

module testbench_top;

integer i, file1;
reg clk = 0;
always #(`T/2) clk = ~clk;
reg comp_enb;

wire [3:0] mem_addr;
wire [63:0] mem_data;
wire mem_read_enb;
wire mem_write_enb;
wire [3:0] res_addr;
wire [63:0] res_data;
wire busyb, done;
// initial
// begin
//     $dumpfile("wave.vcd");
//     $dumpvars(0);
// end

accelerator u_accelerator (
 .clk           (clk)
,.comp_enb      (comp_enb)
,.mem_addr      (mem_addr)
,.mem_data      (mem_data)
,.mem_read_enb  (mem_read_enb)
,.mem_write_enb (mem_write_enb)
,.res_addr      (res_addr)
,.res_data      (res_data)
,.busyb         (busyb)
,.done          (done)
);

ram #(.DATA_WIDTH(64), .ADDR_WIDTH(4)) u_input_mem (
 .clk       (clk)
,.web       (~mem_read_enb)
,.address   (mem_addr)
,.d         ()
,.q         (mem_data)
,.cs        (1'b1)
);

ram #(.DATA_WIDTH(64), .ADDR_WIDTH(4)) u_res_mem (
 .clk       (clk)
,.web       (mem_write_enb)
,.address   (res_addr)
,.d         (res_data)
,.q         (),
.cs         (1'b1)
);

// %%%%%%%%%%%%%%%%%%%%%%%%%%%%%%%%%%%%%%%%%%%%%%%%%%%
initial begin
    // start simulation
    $readmemh("input_mem.csv", u_input_mem.mem);
    comp_enb = 1;
    #(`T) comp_enb = 0;
    
    // finishing simulation
    #(10*`T) begin
        // readout result_memory content to "result_mem.csv"
        file1=$fopen("result_mem.csv","w");
        for(i=0;i<(1<<4);i++)
            $fwrite( file1 , "%8h\n" , u_res_mem.mem[i]);
        $fclose(file1);
        $finish; 
    end
end
endmodule

lab8/lab8_flow_fast/lab8_flow_fast/obj_dir/wave.vcd
$version Generated by VerilatedVcd $end
$timescale 1s $end
 $scope module TOP $end
  $scope module testbench_top $end
   $var wire 32 p i [31:0] $end
   $var wire 32 q file1 [31:0] $end
   $var wire 1 r clk $end
   $var wire 1 s comp_enb $end
   $var wire 4 d mem_addr [3:0] $end
   $var wire 64 t mem_data [63:0] $end
   $var wire 1 C mem_read_enb $end
   $var wire 1 e mem_write_enb $end
   $var wire 4 f res_addr [3:0] $end
   $var wire 64 g res_data [63:0] $end
   $var wire 1 v busyb $end
   $var wire 1 w done $end
   $scope module u_accelerator $end
    $var wire 1 r clk $end
    $var wire 1 s comp_enb $end
    $var wire 4 d mem_addr [3:0] $end
    $var wire 64 t mem_data [63:0] $end
    $var wire 1 C mem_read_enb $end
    $var wire 1 e mem_write_enb $end
    $var wire 4 f res_addr [3:0] $end
    $var wire 64 g res_data [63:0] $end
    $var wire 1 v busyb $end
    $var wire 1 w done $end
    $var wire 32 z S_RST [31:0] $end
    $var wire 32 { S_READ [31:0] $end
    $var wire 32 | S_WORK [31:0] $end
    $var wire 32 } S_DONE [31:0] $end
    $var wire 2 i state [1:0] $end
    $var wire 2 j counter [1:0] $end
    $var wire 64 k reg1 [63:0] $end
    $var wire 64 m reg2 [63:0] $end
   $upscope $end
   $scope module u_input_mem $end
    $var wire 32 ~ DATA_WIDTH [31:0] $end
    $var wire 32 !! ADDR_WIDTH [31:0] $end
    $var wire 32 "! RAM_DEPTH [31:0] $end
    $var wire 1 r clk $end
    $var wire 4 d address [3:0] $end
    $var wire 1 #! cs $end
    $var wire 1 o web $end
    $var wire 64 $! d [63:0] $end
    $var wire 64 t q [63:0] $end
    $var wire 64 t data_out [63:0] $end
    $var wire 64 # mem[0] [63:0] $end
    $var wire 64 % mem[1] [63:0] $end
    $var wire 64 ' mem[2] [63:0] $end
    $var wire 64 ) mem[3] [63:0] $end
    $var wire 64 + mem[4] [63:0] $end
    $var wire 64 - mem[5] [63:0] $end
    $var wire 64 / mem[6] [63:0] $end
    $var wire 64 1 mem[7] [63:0] $end
    $var wire 64 3 mem[8] [63:0] $end
    $var wire 64 5 mem[9] [63:0] $end
    $var wire 64 7 mem[10] [63:0] $end
    $var wire 64 9 mem[11] [63:0] $end
    $var wire 64 ; mem[12] [63:0] $end
    $var wire 64 = mem[13] [63:0] $end
    $var wire 64 ? mem[14] [63:0] $end
    $var wire 64 A mem[15] [63:0] $end
   $upscope $end
   $scope module u_res_mem $end
    $var wire 32 ~ DATA_WIDTH [31:0] $end
    $var wire 32 !! ADDR_WIDTH [31:0] $end
    $var wire 32 "! RAM_DEPTH [31:0] $end
    $var wire 1 r clk $end
    $var wire 4 f address [3:0] $end
    $var wire 1 #! cs $end
    $var wire 1 e web $end
    $var wire 64 g d [63:0] $end
    $var wire 64 x q [63:0] $end
    $var wire 64 x data_out [63:0] $end
    $var wire 64 D mem[0] [63:0] $end
    $var wire 64 F mem[1] [63:0] $end
    $var wire 64 H mem[2] [63:0] $end
    $var wire 64 J mem[3] [63:0] $end
    $var wire 64 L mem[4] [63:0] $end
    $var wire 64 N mem[5] [63:0] $end
    $var wire 64 P mem[6] [63:0] $end
    $var wire 64 R mem[7] [63:0] $end
    $var wire 64 T mem[8] [63:0] $end
    $var wire 64 V mem[9] [63:0] $end
    $var wire 64 X mem[10] [63:0] $end
    $var wire 64 Z mem[11] [63:0] $end
    $var wire 64 \ mem[12] [63:0] $end
    $var wire 64 ^ mem[13] [63:0] $end
    $var wire 64 ` mem[14] [63:0] $end
    $var wire 64 b mem[15] [63:0] $end
   $upscope $end
  $upscope $end
 $upscope $end
$enddefinitions $end


#0
b0100011100000000110110110000000000000000000000000100101000000000 #
b0001100000110010010111111111001000000000000100000001110001100000 %
b0000000011101111011111100010011100000000111001101010010010101001 '
b0000000000000100000000000101100000000000000000000000000000000000 )
b0000000010100000000000001111110111010011101111001101010000000000 +
b0000000001001000000000001010000110100111000000001101000001010001 -
b0001010111011100000000000110011011010110000000001110100110001011 /
b1001100011100001000000000101100100101010001100111010100100100000 1
b0011010000000000010010000000000000000000001010110111100010110111 3
b1001101011100001001000110000000000000000100001100001011110110100 5
b0001000000000000000000000000000001011111001100010001100000000000 7
b0110000111000010100101000000111010110110000000000000000001110101 9
b0000000000111000111001110011000000000000001101100110101100000000 ;
b0000000000000000000000001101010000000000001111010000000001001000 =
b0011011100000010111001000000000001100001110010010101001000110010 ?
b0000000000100101010110111001101001101110100010111101110100000000 A
0C
b0000000000000000000000000000000000000000000000000000000000000000 D
b0000000000000000000000000000000000000000000000000000000000000000 F
b0000000000000000000000000000000000000000000000000000000000000000 H
b0000000000000000000000000000000000000000000000000000000000000000 J
b0000000000000000000000000000000000000000000000000000000000000000 L
b0000000000000000000000000000000000000000000000000000000000000000 N
b0000000000000000000000000000000000000000000000000000000000000000 P
b0000000000000000000000000000000000000000000000000000000000000000 R
b0000000000000000000000000000000000000000000000000000000000000000 T
b0000000000000000000000000000000000000000000000000000000000000000 V
b0000000000000000000000000000000000000000000000000000000000000000 X
b0000000000000000000000000000000000000000000000000000000000000000 Z
b0000000000000000000000000000000000000000000000000000000000000000 \
b0000000000000000000000000000000000000000000000000000000000000000 ^
b0000000000000000000000000000000000000000000000000000000000000000 `
b0000000000000000000000000000000000000000000000000000000000000000 b
b0000 d
0e
b0000 f
b0000000000000000000000000000000000000000000000000000000000000000 g
b00 i
b00 j
b0000000000000000000000000000000000000000000000000000000000000000 k
b0000000000000000000000000000000000000000000000000000000000000000 m
1o
b00000000000000000000000000000000 p
b00000000000000000000000000000000 q
0r
1s
b0100011100000000110110110000000000000000000000000100101000000000 t
1v
0w
b0000000000000000000000000000000000000000000000000000000000000000 x
b00000000000000000000000000000000 z
b00000000000000000000000000000001 {
b00000000000000000000000000000010 |
b00000000000000000000000000000011 }
b00000000000000000000000001000000 ~
b00000000000000000000000000000100 !!
b00000000000000000000000000010000 "!
1#!
b0000000000000000000000000000000000000000000000000000000000000000 $!
#1
1e
1r
#2
0r
0s
#3
b01 i
1r
#4
0r
#5
b01 j
1r
#6
0r
#7
b0001 d
b10 j
b0100011100000000110110110000000000000000000000000100101000000000 k
1r
b0001100000110010010111111111001000000000000100000001110001100000 t
#8
0r
#9
b10 i
b00 j
b0001100000110010010111111111001000000000000100000001110001100000 m
1r
0v
#10
0r
#11
0e
b0010 f
b0101111100110011001110101111001000000000000100000110011001100000 g
b01 j
1r
#12
0r
#13
b0101111100110011001110101111001000000000000100000110011001100000 H
1e
b11 i
b00 j
1r
1w
b0101111100110011001110101111001000000000000100000110011001100000 x
#14
0r
#15
1r
#16
0r
#17
1r
#18
0r
#19
1r
#20
0r
#21
1r
#22
b00000000000000000000000000010000 p
b10000000000000000000000000101100 q
0r
