lab4/t1.v
module PasscodeDetector(
    input clk, data_in, rstb,
    output reg data_out
);

reg [1:0] state;
parameter STAT_IDLE = 0,
            STATE_R1 = 1,
            STATE_R2 = 2,
            STATE_R3 = 3;

always @(state) begin
    if(state==STATE_R3)
        data_out <= 1;
    else
        data_out <= 0;
end

always @(posedge clk or negedge rstb) begin
    if(!rstb)
        state <= STAT_IDLE;
    else
        case(state)
            STAT_IDLE:
                if(data_in==1) //或者写成if(data_in)
                    state <= STATE_R1;
            STATE_R1:
                if(data_in==1)
                    state <= STATE_R2;
                else
                    state <= STAT_IDLE;
            STATE_R2:
                if(data_in==0)//或者写成if(~data_in)或者if(!data_in)
                    state <= STATE_R3;
                else
                    state <= STATE_R2;
            default://STATE_R3,为了可综合必须要有default
                if(data_in==1)
                        state <= STATE_R1;
                    else
                        state <= STAT_IDLE;
        endcase
end

endmodule

lab4/t1_tb.v
`timescale 1ns/1ns
`include "t1.v"

module t1_tb;

reg rstb, clk, data_in;
wire data_out;

PasscodeDetector dut0(
    .clk(clk),
    .data_in(data_in),
    .rstb(rstb),
    .data_out(data_out)
);

initial begin
    $dumpfile("wave_t1.vcd");
    $dumpvars(0);
    $monitor("time=%4t,clk=%1b, rstb=%1b, data_in=%1b, data_out=%1b",$time,clk,rstb,data_in,data_out);
end

initial begin
    clk = 0;
    forever #5 clk = ~clk;
end

initial begin
    rstb = 1;
    data_in = 0;
    #1 rstb = 0;
    #10 rstb = 1;
    #10 data_in = 1;
    #10 data_in = 0;
    #10 data_in = 1;
    #10 data_in = 1;
    #10 data_in = 0;    
    #10 data_in = 1;
    #10 data_in = 1;
    #10 data_in = 1;
    #10 data_in = 0; 
    #10 data_in = 0; 
    #10 $finish;
end

endmodule

lab4/wave_t1.vcd
$date
	Sat May 16 14:14:51 2026
$end
$version
	Icarus Verilog
$end
$timescale
	1ns
$end
$scope module t1_tb $end
$var wire 1 ! data_out $end
$var reg 1 " clk $end
$var reg 1 # data_in $end
$var reg 1 $ rstb $end
$scope module dut0 $end
$var wire 1 " clk $end
$var wire 1 # data_in $end
$var wire 1 $ rstb $end
$var reg 1 ! data_out $end
$var reg 2 % state [1:0] $end
$upscope $end
$upscope $end
$enddefinitions $end
#0
$dumpvars
bx %
1$
0#
0"
x!
$end
#1
0!
b0 %
0$
#5
1"
#10
0"
#11
1$
#15
1"
#20
0"
#21
1#
#25
b1 %
1"
#30
0"
#31
0#
#35
b0 %
1"
#40
0"
#41
1#
#45
b1 %
1"
#50
0"
#55
b10 %
1"
#60
0"
#61
0#
#65
1!
b11 %
1"
#70
0"
#71
1#
#75
0!
b1 %
1"
#80
0"
#85
b10 %
1"
#90
0"
#95
1"
#100
0"
#101
0#
#105
1!
b11 %
1"
#110
0"
#115
0!
b0 %
1"
