lab4/t2.v
module verilog_fsm (clk, reset, sa, sb, la,lb);
    input  clk, reset;
    input sa,sb;
    output reg [1:0] la,lb;
    parameter state_0 = 2'b00;
    parameter state_1 = 2'b01;
    parameter state_2 = 2'b10;
    parameter state_3 = 2'b11;
    localparam GREEN  = 2'b00;
    localparam YELLOW = 2'b01;
    localparam RED    = 2'b10;
    reg [1:0] state, next_state;
    reg [3:0] counter;
    always @ (posedge clk or posedge reset)
    begin
        if (reset) begin
            state <= state_0;
            counter <= 4'b0000;
        end
        else begin
            state <= next_state;
            if ((state == state_0 || state == state_2) && (sa && sb)) begin
                if (counter < 6)
                    counter <= counter + 1'b1;
            end 
            else begin
                counter <= 4'b0000;
            end
        end
    end
    always @ (*)
    begin
        case (state)
            state_0: begin
                if ((sa && ~sb) || (sa && sb && counter >= 5))begin
                    next_state=state_1;
                end
                else begin
                    next_state=state_0;
                end
            end
            state_1: begin
                next_state = state_2;
            end    
            state_2: begin
                if ((sb==1 && sa==0) || (sa==1 && sb==1 && counter >= 5))begin
                    next_state=state_3;
                end
                else begin 
                    next_state=state_2;
                end
            end
            state_3: begin
                next_state = state_0;
            end
            default:begin
                next_state = state_0;
            end
        endcase
    end
    always @(*) begin
        case (state)
            state_0: begin lb = GREEN;  la = RED;    end
            state_1: begin lb = YELLOW; la = RED;    end
            state_2: begin lb = RED;    la = GREEN;  end
            state_3: begin lb = RED;    la = YELLOW; end
            default: begin lb = RED;    la = RED;    end
        endcase
    end
endmodule

lab4/t2_tb.v
`timescale 1ms/1ms
`include "t2.v"

module t2_tb;

reg reset, clk, sa, sb;
wire [1:0] la, lb;

verilog_fsm dut0(
    .clk(clk),
    .reset(reset),
    .sa(sa),
    .sb(sb),
    .la(la),
    .lb(lb)
);

initial begin
    $dumpfile("wave_t2.vcd");
    $dumpvars(0);
    $monitor("time=%4t,clk=%1b, reset=%1b, sa=%1b, sb=%1b, la=%2b, lb=%2b",$time,clk,reset,sa,sb,la,lb);
end

initial begin
    clk = 0;
    forever #2500 clk = ~clk;
end

initial begin
    reset = 0;
    sa = 0;
    sb = 0;
    #500 reset = 1;      
    #5000 reset = 0;     
    #5000 sa = 1;              
    #5000 sb = 1;                
    #60000 sa = 0;
    #10000 sb = 0;
    #10000 $finish;
end

endmodule

lab4/wave_t2.vcd
$date
	Sat May 16 21:50:02 2026
$end
$version
	Icarus Verilog
$end
$timescale
	1ms
$end
$scope module t2_tb $end
$var wire 2 ! lb [1:0] $end
$var wire 2 " la [1:0] $end
$var reg 1 # clk $end
$var reg 1 $ reset $end
$var reg 1 % sa $end
$var reg 1 & sb $end
$scope module dut0 $end
$var wire 1 # clk $end
$var wire 1 $ reset $end
$var wire 1 % sa $end
$var wire 1 & sb $end
$var reg 4 ' counter [3:0] $end
$var reg 2 ( la [1:0] $end
$var reg 2 ) lb [1:0] $end
$var reg 2 * next_state [1:0] $end
$var reg 2 + state [1:0] $end
$upscope $end
$upscope $end
$enddefinitions $end
#0
$dumpvars
bx +
b0 *
bx )
bx (
bx '
0&
0%
0$
0#
bx "
bx !
$end
#500
b10 "
b10 (
b0 !
b0 )
b0 '
b0 +
1$
#2500
1#
#5000
0#
#5500
0$
#7500
1#
#10000
0#
#10500
b1 *
1%
#12500
b1 !
b1 )
b10 *
b1 +
1#
#15000
0#
#15500
1&
#17500
b0 "
b0 (
b10 !
b10 )
b10 +
1#
#20000
0#
#22500
b1 '
1#
#25000
0#
#27500
b10 '
1#
#30000
0#
#32500
b11 '
1#
#35000
0#
#37500
b100 '
1#
#40000
0#
#42500
b11 *
b101 '
1#
#45000
0#
#47500
b1 "
b1 (
b0 *
b110 '
b11 +
1#
#50000
0#
#52500
b10 "
b10 (
b0 !
b0 )
b0 '
b0 +
1#
#55000
0#
#57500
b1 '
1#
#60000
0#
#62500
b10 '
1#
#65000
0#
#67500
b11 '
1#
#70000
0#
#72500
b100 '
1#
#75000
0#
#75500
0%
#77500
b0 '
1#
#80000
0#
#82500
1#
#85000
0#
#85500
0&
