lab5/uart.v
//////////////////////////////////////////////////////////////////////////////////
//                                                                              //
//                                                                              //
//  Author: meisq                                                               //
//          msq@qq.com                                                          //
//          ALINX(shanghai) Technology Co.,Ltd                                  //
//          heijin                                                              //
//     WEB: http://www.alinx.cn/                                                //
//     BBS: http://www.heijin.org/                                              //
//                                                                              //
//////////////////////////////////////////////////////////////////////////////////
//                                                                              //
// Copyright (c) 2017,ALINX(shanghai) Technology Co.,Ltd                        //
//                    All rights reserved                                       //
//                                                                              //
// This source file may be used and distributed without restriction provided    //
// that this copyright statement is not removed from the file and that any      //
// derivative work contains the original copyright notice and the associated    //
// disclaimer.                                                                  //
//                                                                              //
//////////////////////////////////////////////////////////////////////////////////

//================================================================================
//  Revision History:
//  Date          By            Revision    Change Description
//--------------------------------------------------------------------------------
//2017/8/1                    1.0          Original
//*******************************************************************************/
module uart_tx
#(
	parameter CLK_FRE = 50,      //clock frequency(Mhz)
	parameter BAUD_RATE = 115200 //serial baud rate
)
(
	input                        clk,              //clock input
	input                        rst_n,            //asynchronous reset input, low active 
	input[7:0]                   tx_data,          //data to send
	input                        tx_data_valid,    //data to be sent is valid
	output reg                   tx_data_ready,    //send ready
	output                       tx_pin            //serial data output
);
//calculates the clock cycle for baud rate 
localparam                       CYCLE = CLK_FRE * 1000000 / BAUD_RATE;
//state machine code
localparam                       S_IDLE       = 1;
localparam                       S_START      = 2;//start bit
localparam                       S_SEND_BYTE  = 3;//data bits
localparam                       S_STOP       = 4;//stop bit
reg[2:0]                         state;
reg[2:0]                         next_state;
reg[15:0]                        cycle_cnt; //baud counter
reg[2:0]                         bit_cnt;//bit counter
reg[7:0]                         tx_data_latch; //latch data to send
reg                              tx_reg; //serial data output
assign tx_pin = tx_reg;
always@(posedge clk or negedge rst_n)
begin
	if(rst_n == 1'b0)
		state <= S_IDLE;
	else
		state <= next_state;
end

always@(*)
begin
	case(state)
		S_IDLE:
			if(tx_data_valid == 1'b1)
				next_state <= S_START;
			else
				next_state <= S_IDLE;
		S_START:
			if(cycle_cnt == CYCLE - 1)
				next_state <= S_SEND_BYTE;
			else
				next_state <= S_START;
		S_SEND_BYTE:
			if(cycle_cnt == CYCLE - 1  && bit_cnt == 3'd7)
				next_state <= S_STOP;
			else
				next_state <= S_SEND_BYTE;
		S_STOP:
			if(cycle_cnt == CYCLE - 1)
				next_state <= S_IDLE;
			else
				next_state <= S_STOP;
		default:
			next_state <= S_IDLE;
	endcase
end
always@(posedge clk or negedge rst_n)
begin
	if(rst_n == 1'b0)
		begin
			tx_data_ready <= 1'b0;
		end
	else if(state == S_IDLE)
		if(tx_data_valid == 1'b1)
			tx_data_ready <= 1'b0;
		else
			tx_data_ready <= 1'b1;
	else if(state == S_STOP && cycle_cnt == CYCLE - 1)
			tx_data_ready <= 1'b1;
end


always@(posedge clk or negedge rst_n)
begin
	if(rst_n == 1'b0)
		begin
			tx_data_latch <= 8'd0;
		end
	else if(state == S_IDLE && tx_data_valid == 1'b1)
			tx_data_latch <= tx_data;
		
end

always@(posedge clk or negedge rst_n)
begin
	if(rst_n == 1'b0)
		begin
			bit_cnt <= 3'd0;
		end
	else if(state == S_SEND_BYTE)
		if(cycle_cnt == CYCLE - 1)
			bit_cnt <= bit_cnt + 3'd1;
		else
			bit_cnt <= bit_cnt;
	else
		bit_cnt <= 3'd0;
end


always@(posedge clk or negedge rst_n)
begin
	if(rst_n == 1'b0)
		cycle_cnt <= 16'd0;
	else if((state == S_SEND_BYTE && cycle_cnt == CYCLE - 1) || next_state != state)
		cycle_cnt <= 16'd0;
	else
		cycle_cnt <= cycle_cnt + 16'd1;	
end

always@(posedge clk or negedge rst_n)
begin
	if(rst_n == 1'b0)
		tx_reg <= 1'b1;
	else
		case(state)
			S_IDLE,S_STOP:
				tx_reg <= 1'b1; 
			S_START:
				tx_reg <= 1'b0; 
			S_SEND_BYTE:
				tx_reg <= tx_data_latch[bit_cnt];
			default:
				tx_reg <= 1'b1; 
		endcase
end

endmodule 


//////////////////////////////////////////////////////////////////////////////////
//                                                                              //
//                                                                              //
//  Author: meisq                                                               //
//          msq@qq.com                                                          //
//          ALINX(shanghai) Technology Co.,Ltd                                  //
//          heijin                                                              //
//     WEB: http://www.alinx.cn/                                                //
//     BBS: http://www.heijin.org/                                              //
//                                                                              //
//////////////////////////////////////////////////////////////////////////////////
//                                                                              //
// Copyright (c) 2017,ALINX(shanghai) Technology Co.,Ltd                        //
//                    All rights reserved                                       //
//                                                                              //
// This source file may be used and distributed without restriction provided    //
// that this copyright statement is not removed from the file and that any      //
// derivative work contains the original copyright notice and the associated    //
// disclaimer.                                                                  //
//                                                                              //
//////////////////////////////////////////////////////////////////////////////////

//================================================================================
//  Revision History:
//  Date          By            Revision    Change Description
//--------------------------------------------------------------------------------
//2017/8/1                    1.0          Original
//*******************************************************************************/
module uart_rx
#(
	parameter CLK_FRE = 50,      //clock frequency(Mhz)
	parameter BAUD_RATE = 115200 //serial baud rate
)
(
	input                        clk,              //clock input
	input                        rst_n,            //asynchronous reset input, low active 
	output reg[7:0]              rx_data,          //received serial data
	output reg                   rx_data_valid,    //received serial data is valid
	input                        rx_data_ready,    //data receiver module ready
	input                        rx_pin            //serial data input
);
//calculates the clock cycle for baud rate 
localparam                       CYCLE = CLK_FRE * 1000000 / BAUD_RATE;
//state machine code
localparam                       S_IDLE      = 1;
localparam                       S_START     = 2; //start bit
localparam                       S_REC_BYTE  = 3; //data bits
localparam                       S_STOP      = 4; //stop bit
localparam                       S_DATA      = 5;

reg[2:0]                         state;
reg[2:0]                         next_state;
reg                              rx_d0;            //delay 1 clock for rx_pin
reg                              rx_d1;            //delay 1 clock for rx_d0
wire                             rx_negedge;       //negedge of rx_pin
reg[7:0]                         rx_bits;          //temporary storage of received data
reg[15:0]                        cycle_cnt;        //baud counter
reg[2:0]                         bit_cnt;          //bit counter

assign rx_negedge = rx_d1 && ~rx_d0;

always@(posedge clk or negedge rst_n)
begin
	if(rst_n == 1'b0)
	begin
		rx_d0 <= 1'b0;
		rx_d1 <= 1'b0;	
	end
	else
	begin
		rx_d0 <= rx_pin;
		rx_d1 <= rx_d0;
	end
end


always@(posedge clk or negedge rst_n)
begin
	if(rst_n == 1'b0)
		state <= S_IDLE;
	else
		state <= next_state;
end

always@(*)
begin
	case(state)
		S_IDLE:
			if(rx_negedge)
				next_state <= S_START;
			else
				next_state <= S_IDLE;
		S_START:
			if(cycle_cnt == CYCLE - 1)//one data cycle 
				next_state <= S_REC_BYTE;
			else
				next_state <= S_START;
		S_REC_BYTE:
			if(cycle_cnt == CYCLE - 1  && bit_cnt == 3'd7)  //receive 8bit data
				next_state <= S_STOP;
			else
				next_state <= S_REC_BYTE;
		S_STOP:
			if(cycle_cnt == CYCLE/2 - 1)//half bit cycle,to avoid missing the next byte receiver
				next_state <= S_DATA;
			else
				next_state <= S_STOP;
		S_DATA:
			if(rx_data_ready)    //data receive complete
				next_state <= S_IDLE;
			else
				next_state <= S_DATA;
		default:
			next_state <= S_IDLE;
	endcase
end

always@(posedge clk or negedge rst_n)
begin
	if(rst_n == 1'b0)
		rx_data_valid <= 1'b0;
	else if(state == S_STOP && next_state != state)
		rx_data_valid <= 1'b1;
	else if(state == S_DATA && rx_data_ready)
		rx_data_valid <= 1'b0;
end

always@(posedge clk or negedge rst_n)
begin
	if(rst_n == 1'b0)
		rx_data <= 8'd0;
	else if(state == S_STOP && next_state != state)
		rx_data <= rx_bits;//latch received data
end

always@(posedge clk or negedge rst_n)
begin
	if(rst_n == 1'b0)
		begin
			bit_cnt <= 3'd0;
		end
	else if(state == S_REC_BYTE)
		if(cycle_cnt == CYCLE - 1)
			bit_cnt <= bit_cnt + 3'd1;
		else
			bit_cnt <= bit_cnt;
	else
		bit_cnt <= 3'd0;
end


always@(posedge clk or negedge rst_n)
begin
	if(rst_n == 1'b0)
		cycle_cnt <= 16'd0;
	else if((state == S_REC_BYTE && cycle_cnt == CYCLE - 1) || next_state != state)
		cycle_cnt <= 16'd0;
	else
		cycle_cnt <= cycle_cnt + 16'd1;	
end
//receive serial data bit data
always@(posedge clk or negedge rst_n)
begin
	if(rst_n == 1'b0)
		rx_bits <= 8'd0;
	else if(state == S_REC_BYTE && cycle_cnt == CYCLE/2 - 1)
		rx_bits[bit_cnt] <= rx_pin;
	else
		rx_bits <= rx_bits; 
end
endmodule

lab5/test.v
module test1
(
input	sys_clk,     //system clock 50Mhz on board
input	rstb,      //reset ,low active
output	uart_tx    //fpga send data
);

parameter CLK_FRE = 50;//Mhz
localparam [1:0] STATE_RESET = 0, STATE_SEND = 3;
// communication interface
reg [7:0] 	tx_data;
reg 		tx_data_valid;

reg [1:0] 	state;

// State transfer
always@(posedge sys_clk or negedge rstb)
begin
	if(~rstb)
	begin
		tx_data 		<= 8'd0;
		tx_data_valid 	<= 0;
		state 			<= STATE_RESET;
	end
	else
		case(state)
			STATE_SEND: begin
				if(tx_data_valid && tx_data_ready)//last byte sent is complete
				begin
					// "6" is 8'b00110110;
					// send from LSB to MSB: 01101100
					tx_data <= "6";
					tx_data_valid <= 1'b0;
				end
				else if(~tx_data_valid)
				begin
					tx_data_valid <= 1'b1;
				end
			end
			default: begin//STATE_RESET
				state 	<= STATE_SEND;
			end
		endcase
end

// UART Interface
uart_tx #
(
.CLK_FRE(CLK_FRE),
.BAUD_RATE(115200)
) uart_tx_inst
(
.clk 			(sys_clk),
.rst_n 			(rstb),
.tx_data  		(tx_data),
.tx_data_valid	(tx_data_valid),
.tx_data_ready	(tx_data_ready),
.tx_pin 		(uart_tx)
);
endmodule

lab5/test_tb.v
`timescale 1ns/1ns
`include "uart.v"
`include "test.v"
module test_top;

reg sys_clk = 0;
reg rstb = 0;
reg uart_rx = 0;
wire uart_tx;

always #1 sys_clk = ~sys_clk;

initial begin
	#2 rstb = 1;
	#100000 $finish;
end

initial begin
	$dumpfile("wave.vcd");
	$dumpvars(0,test_top);
end

test1 u1(
.sys_clk(sys_clk),
.rstb(rstb),
.uart_tx(uart_tx)
);

endmodule

lab5/wave.vcd
$date
	Wed May 20 16:31:39 2026
$end
$version
	Icarus Verilog
$end
$timescale
	1ns
$end
$scope module test_top $end
$var wire 1 ! uart_tx $end
$var reg 1 " rstb $end
$var reg 1 # sys_clk $end
$var reg 1 $ uart_rx $end
$scope module u1 $end
$var wire 1 " rstb $end
$var wire 1 # sys_clk $end
$var wire 1 ! uart_tx $end
$var wire 1 % tx_data_ready $end
$var reg 2 & state [1:0] $end
$var reg 8 ' tx_data [7:0] $end
$var reg 1 ( tx_data_valid $end
$scope module uart_tx_inst $end
$var wire 1 # clk $end
$var wire 1 " rst_n $end
$var wire 8 ) tx_data [7:0] $end
$var wire 1 ( tx_data_valid $end
$var wire 1 ! tx_pin $end
$var reg 3 * bit_cnt [2:0] $end
$var reg 16 + cycle_cnt [15:0] $end
$var reg 3 , next_state [2:0] $end
$var reg 3 - state [2:0] $end
$var reg 8 . tx_data_latch [7:0] $end
$var reg 1 % tx_data_ready $end
$var reg 1 / tx_reg $end
$upscope $end
$upscope $end
$upscope $end
$enddefinitions $end
#0
$dumpvars
1/
b0 .
b1 -
b1 ,
b0 +
b0 *
b110110 )
0(
b110110 '
b0 &
0%
0$
0#
0"
1!
$end
#1
1#
#2
0#
1"
#3
1%
b1 +
b11 &
1#
#4
0#
#5
b10 ,
1(
b10 +
1#
#6
0#
#7
b10 -
0%
b110110 .
b0 +
0(
1#
#8
0#
#9
1(
0!
0/
b1 +
1#
#10
0#
#11
b10 +
1#
#12
0#
#13
b11 +
1#
#14
0#
#15
b100 +
1#
#16
0#
#17
b101 +
1#
#18
0#
#19
b110 +
1#
#20
0#
#21
b111 +
1#
#22
0#
#23
b1000 +
1#
#24
0#
#25
b1001 +
1#
#26
0#
#27
b1010 +
1#
#28
0#
#29
b1011 +
1#
#30
0#
#31
b1100 +
1#
#32
0#
#33
b1101 +
1#
#34
0#
#35
b1110 +
1#
#36
0#
#37
b1111 +
1#
#38
0#
#39
b10000 +
1#
#40
0#
#41
b10001 +
1#
#42
0#
#43
b10010 +
1#
#44
0#
#45
b10011 +
1#
#46
0#
#47
b10100 +
1#
#48
0#
#49
b10101 +
1#
#50
0#
#51
b10110 +
1#
#52
0#
#53
b10111 +
1#
#54
0#
#55
b11000 +
1#
#56
0#
#57
b11001 +
1#
#58
0#
#59
b11010 +
1#
#60
0#
#61
b11011 +
1#
#62
0#
#63
b11100 +
1#
#64
0#
#65
b11101 +
1#
#66
0#
#67
b11110 +
1#
#68
0#
#69
b11111 +
1#
#70
0#
#71
b100000 +
1#
#72
0#
#73
b100001 +
1#
#74
0#
#75
b100010 +
1#
#76
0#
#77
b100011 +
1#
#78
0#
#79
b100100 +
1#
#80
0#
#81
b100101 +
1#
#82
0#
#83
b100110 +
1#
#84
0#
#85
b100111 +
1#
#86
0#
#87
b101000 +
1#
#88
0#
#89
b101001 +
1#
#90
0#
#91
b101010 +
1#
#92
0#
#93
b101011 +
1#
#94
0#
#95
b101100 +
1#
#96
0#
#97
b101101 +
1#
#98
0#
#99
b101110 +
1#
#100
0#
#101
b101111 +
1#
#102
0#
#103
b110000 +
1#
#104
0#
#105
b110001 +
1#
#106
0#
#107
b110010 +
1#
#108
0#
#109
b110011 +
1#
#110
0#
#111
b110100 +
1#
#112
0#
#113
b110101 +
1#
#114
0#
#115
b110110 +
1#
#116
0#
#117
b110111 +
1#
#118
0#
#119
b111000 +
1#
#120
0#
#121
b111001 +
1#
#122
0#
#123
b111010 +
1#
#124
0#
#125
b111011 +
1#
#126
0#
#127
b111100 +
1#
#128
0#
#129
b111101 +
1#
#130
0#
#131
b111110 +
1#
#132
0#
#133
b111111 +
1#
#134
0#
#135
b1000000 +
1#
#136
0#
#137
b1000001 +
1#
#138
0#
#139
b1000010 +
1#
#140
0#
#141
b1000011 +
1#
#142
0#
#143
b1000100 +
1#
#144
0#
#145
b1000101 +
1#
#146
0#
#147
b1000110 +
1#
#148
0#
#149
b1000111 +
1#
#150
0#
#151
b1001000 +
1#
#152
0#
#153
b1001001 +
1#
#154
0#
#155
b1001010 +
1#
#156
0#
#157
b1001011 +
1#
#158
0#
#159
b1001100 +
1#
#160
0#
#161
b1001101 +
1#
#162
0#
#163
b1001110 +
1#
#164
0#
#165
b1001111 +
1#
#166
0#
#167
b1010000 +
1#
#168
0#
#169
b1010001 +
1#
#170
0#
#171
b1010010 +
1#
#172
0#
#173
b1010011 +
1#
#174
0#
#175
b1010100 +
1#
#176
0#
#177
b1010101 +
1#
#178
0#
#179
b1010110 +
1#
#180
0#
#181
b1010111 +
1#
#182
0#
#183
b1011000 +
1#
#184
0#
#185
b1011001 +
1#
#186
0#
#187
b1011010 +
1#
#188
0#
#189
b1011011 +
1#
#190
0#
#191
b1011100 +
1#
#192
0#
#193
b1011101 +
1#
#194
0#
#195
b1011110 +
1#
#196
0#
#197
b1011111 +
1#
#198
0#
#199
b1100000 +
1#
#200
0#
#201
b1100001 +
1#
#202
0#
#203
b1100010 +
1#
#204
0#
#205
b1100011 +
1#
#206
0#
#207
b1100100 +
1#
#208
0#
#209
b1100101 +
1#
#210
0#
#211
b1100110 +
1#
#212
0#
#213
b1100111 +
1#
#214
0#
#215
b1101000 +
1#
#216
0#
#217
b1101001 +
1#
#218
0#
#219
b1101010 +
1#
#220
0#
#221
b1101011 +
1#
#222
0#
#223
b1101100 +
1#
#224
0#
#225
b1101101 +
1#
#226
0#
#227
b1101110 +
1#
#228
0#
#229
b1101111 +
1#
#230
0#
#231
b1110000 +
1#
#232
0#
#233
b1110001 +
1#
#234
0#
#235
b1110010 +
1#
#236
0#
#237
b1110011 +
1#
#238
0#
#239
b1110100 +
1#
#240
0#
#241
b1110101 +
1#
#242
0#
#243
b1110110 +
1#
#244
0#
#245
b1110111 +
1#
#246
0#
#247
b1111000 +
1#
#248
0#
#249
b1111001 +
1#
#250
0#
#251
b1111010 +
1#
#252
0#
#253
b1111011 +
1#
#254
0#
#255
b1111100 +
1#
#256
0#
#257
b1111101 +
1#
#258
0#
#259
b1111110 +
1#
#260
0#
#261
b1111111 +
1#
#262
0#
#263
b10000000 +
1#
#264
0#
#265
b10000001 +
1#
#266
0#
#267
b10000010 +
1#
#268
0#
#269
b10000011 +
1#
#270
0#
#271
b10000100 +
1#
#272
0#
#273
b10000101 +
1#
#274
0#
#275
b10000110 +
1#
#276
0#
#277
b10000111 +
1#
#278
0#
#279
b10001000 +
1#
#280
0#
#281
b10001001 +
1#
#282
0#
#283
b10001010 +
1#
#284
0#
#285
b10001011 +
1#
#286
0#
#287
b10001100 +
1#
#288
0#
#289
b10001101 +
1#
#290
0#
#291
b10001110 +
1#
#292
0#
#293
b10001111 +
1#
#294
0#
#295
b10010000 +
1#
#296
0#
#297
b10010001 +
1#
#298
0#
#299
b10010010 +
1#
#300
0#
#301
b10010011 +
1#
#302
0#
#303
b10010100 +
1#
#304
0#
#305
b10010101 +
1#
#306
0#
#307
b10010110 +
1#
#308
0#
#309
b10010111 +
1#
#310
0#
#311
b10011000 +
1#
#312
0#
#313
b10011001 +
1#
#314
0#
#315
b10011010 +
1#
#316
0#
#317
b10011011 +
1#
#318
0#
#319
b10011100 +
1#
#320
0#
#321
b10011101 +
1#
#322
0#
#323
b10011110 +
1#
#324
0#
#325
b10011111 +
1#
#326
0#
#327
b10100000 +
1#
#328
0#
#329
b10100001 +
1#
#330
0#
#331
b10100010 +
1#
#332
0#
#333
b10100011 +
1#
#334
0#
#335
b10100100 +
1#
#336
0#
#337
b10100101 +
1#
#338
0#
#339
b10100110 +
1#
#340
0#
#341
b10100111 +
1#
#342
0#
#343
b10101000 +
1#
#344
0#
#345
b10101001 +
1#
#346
0#
#347
b10101010 +
1#
#348
0#
#349
b10101011 +
1#
#350
0#
#351
b10101100 +
1#
#352
0#
#353
b10101101 +
1#
#354
0#
#355
b10101110 +
1#
#356
0#
#357
b10101111 +
1#
#358
0#
#359
b10110000 +
1#
#360
0#
#361
b10110001 +
1#
#362
0#
#363
b10110010 +
1#
#364
0#
#365
b10110011 +
1#
#366
0#
#367
b10110100 +
1#
#368
0#
#369
b10110101 +
1#
#370
0#
#371
b10110110 +
1#
#372
0#
#373
b10110111 +
1#
#374
0#
#375
b10111000 +
1#
#376
0#
#377
b10111001 +
1#
#378
0#
#379
b10111010 +
1#
#380
0#
#381
b10111011 +
1#
#382
0#
#383
b10111100 +
1#
#384
0#
#385
b10111101 +
1#
#386
0#
#387
b10111110 +
1#
#388
0#
#389
b10111111 +
1#
#390
0#
#391
b11000000 +
1#
#392
0#
#393
b11000001 +
1#
#394
0#
#395
b11000010 +
1#
#396
0#
#397
b11000011 +
1#
#398
0#
#399
b11000100 +
1#
#400
0#
#401
b11000101 +
1#
#402
0#
#403
b11000110 +
1#
#404
0#
#405
b11000111 +
1#
#406
0#
#407
b11001000 +
1#
#408
0#
#409
b11001001 +
1#
#410
0#
#411
b11001010 +
1#
#412
0#
#413
b11001011 +
1#
#414
0#
#415
b11001100 +
1#
#416
0#
#417
b11001101 +
1#
#418
0#
#419
b11001110 +
1#
#420
0#
#421
b11001111 +
1#
#422
0#
#423
b11010000 +
1#
#424
0#
#425
b11010001 +
1#
#426
0#
#427
b11010010 +
1#
#428
0#
#429
b11010011 +
1#
#430
0#
#431
b11010100 +
1#
#432
0#
#433
b11010101 +
1#
#434
0#
#435
b11010110 +
1#
#436
0#
#437
b11010111 +
1#
#438
0#
#439
b11011000 +
1#
#440
0#
#441
b11011001 +
1#
#442
0#
#443
b11011010 +
1#
#444
0#
#445
b11011011 +
1#
#446
0#
#447
b11011100 +
1#
#448
0#
#449
b11011101 +
1#
#450
0#
#451
b11011110 +
1#
#452
0#
#453
b11011111 +
1#
#454
0#
#455
b11100000 +
1#
#456
0#
#457
b11100001 +
1#
#458
0#
#459
b11100010 +
1#
#460
0#
#461
b11100011 +
1#
#462
0#
#463
b11100100 +
1#
#464
0#
#465
b11100101 +
1#
#466
0#
#467
b11100110 +
1#
#468
0#
#469
b11100111 +
1#
#470
0#
#471
b11101000 +
1#
#472
0#
#473
b11101001 +
1#
#474
0#
#475
b11101010 +
1#
#476
0#
#477
b11101011 +
1#
#478
0#
#479
b11101100 +
1#
#480
0#
#481
b11101101 +
1#
#482
0#
#483
b11101110 +
1#
#484
0#
#485
b11101111 +
1#
#486
0#
#487
b11110000 +
1#
#488
0#
#489
b11110001 +
1#
#490
0#
#491
b11110010 +
1#
#492
0#
#493
b11110011 +
1#
#494
0#
#495
b11110100 +
1#
#496
0#
#497
b11110101 +
1#
#498
0#
#499
b11110110 +
1#
#500
0#
#501
b11110111 +
1#
#502
0#
#503
b11111000 +
1#
#504
0#
#505
b11111001 +
1#
#506
0#
#507
b11111010 +
1#
#508
0#
#509
b11111011 +
1#
#510
0#
#511
b11111100 +
1#
#512
0#
#513
b11111101 +
1#
#514
0#
#515
b11111110 +
1#
#516
0#
#517
b11111111 +
1#
#518
0#
#519
b100000000 +
1#
#520
0#
#521
b100000001 +
1#
#522
0#
#523
b100000010 +
1#
#524
0#
#525
b100000011 +
1#
#526
0#
#527
b100000100 +
1#
#528
0#
#529
b100000101 +
1#
#530
0#
#531
b100000110 +
1#
#532
0#
#533
b100000111 +
1#
#534
0#
#535
b100001000 +
1#
#536
0#
#537
b100001001 +
1#
#538
0#
#539
b100001010 +
1#
#540
0#
#541
b100001011 +
1#
#542
0#
#543
b100001100 +
1#
#544
0#
#545
b100001101 +
1#
#546
0#
#547
b100001110 +
1#
#548
0#
#549
b100001111 +
1#
#550
0#
#551
b100010000 +
1#
#552
0#
#553
b100010001 +
1#
#554
0#
#555
b100010010 +
1#
#556
0#
#557
b100010011 +
1#
#558
0#
#559
b100010100 +
1#
#560
0#
#561
b100010101 +
1#
#562
0#
#563
b100010110 +
1#
#564
0#
#565
b100010111 +
1#
#566
0#
#567
b100011000 +
1#
#568
0#
#569
b100011001 +
1#
#570
0#
#571
b100011010 +
1#
#572
0#
#573
b100011011 +
1#
#574
0#
#575
b100011100 +
1#
#576
0#
#577
b100011101 +
1#
#578
0#
#579
b100011110 +
1#
#580
0#
#581
b100011111 +
1#
#582
0#
#583
b100100000 +
1#
#584
0#
#585
b100100001 +
1#
#586
0#
#587
b100100010 +
1#
#588
0#
#589
b100100011 +
1#
#590
0#
#591
b100100100 +
1#
#592
0#
#593
b100100101 +
1#
#594
0#
#595
b100100110 +
1#
#596
0#
#597
b100100111 +
1#
#598
0#
#599
b100101000 +
1#
#600
0#
#601
b100101001 +
1#
#602
0#
#603
b100101010 +
1#
#604
0#
#605
b100101011 +
1#
#606
0#
#607
b100101100 +
1#
#608
0#
#609
b100101101 +
1#
#610
0#
#611
b100101110 +
1#
#612
0#
#613
b100101111 +
1#
#614
0#
#615
b100110000 +
1#
#616
0#
#617
b100110001 +
1#
#618
0#
#619
b100110010 +
1#
#620
0#
#621
b100110011 +
1#
#622
0#
#623
b100110100 +
1#
#624
0#
#625
b100110101 +
1#
#626
0#
#627
b100110110 +
1#
#628
0#
#629
b100110111 +
1#
#630
0#
#631
b100111000 +
1#
#632
0#
#633
b100111001 +
1#
#634
0#
#635
b100111010 +
1#
#636
0#
#637
b100111011 +
1#
#638
0#
#639
b100111100 +
1#
#640
0#
#641
b100111101 +
1#
#642
0#
#643
b100111110 +
1#
#644
0#
#645
b100111111 +
1#
#646
0#
#647
b101000000 +
1#
#648
0#
#649
b101000001 +
1#
#650
0#
#651
b101000010 +
1#
#652
0#
#653
b101000011 +
1#
#654
0#
#655
b101000100 +
1#
#656
0#
#657
b101000101 +
1#
#658
0#
#659
b101000110 +
1#
#660
0#
#661
b101000111 +
1#
#662
0#
#663
b101001000 +
1#
#664
0#
#665
b101001001 +
1#
#666
0#
#667
b101001010 +
1#
#668
0#
#669
b101001011 +
1#
#670
0#
#671
b101001100 +
1#
#672
0#
#673
b101001101 +
1#
#674
0#
#675
b101001110 +
1#
#676
0#
#677
b101001111 +
1#
#678
0#
#679
b101010000 +
1#
#680
0#
#681
b101010001 +
1#
#682
0#
#683
b101010010 +
1#
#684
0#
#685
b101010011 +
1#
#686
0#
#687
b101010100 +
1#
#688
0#
#689
b101010101 +
1#
#690
0#
#691
b101010110 +
1#
#692
0#
#693
b101010111 +
1#
#694
0#
#695
b101011000 +
1#
#696
0#
#697
b101011001 +
1#
#698
0#
#699
b101011010 +
1#
#700
0#
#701
b101011011 +
1#
#702
0#
#703
b101011100 +
1#
#704
0#
#705
b101011101 +
1#
#706
0#
#707
b101011110 +
1#
#708
0#
#709
b101011111 +
1#
#710
0#
#711
b101100000 +
1#
#712
0#
#713
b101100001 +
1#
#714
0#
#715
b101100010 +
1#
#716
0#
#717
b101100011 +
1#
#718
0#
#719
b101100100 +
1#
#720
0#
#721
b101100101 +
1#
#722
0#
#723
b101100110 +
1#
#724
0#
#725
b101100111 +
1#
#726
0#
#727
b101101000 +
1#
#728
0#
#729
b101101001 +
1#
#730
0#
#731
b101101010 +
1#
#732
0#
#733
b101101011 +
1#
#734
0#
#735
b101101100 +
1#
#736
0#
#737
b101101101 +
1#
#738
0#
#739
b101101110 +
1#
#740
0#
#741
b101101111 +
1#
#742
0#
#743
b101110000 +
1#
#744
0#
#745
b101110001 +
1#
#746
0#
#747
b101110010 +
1#
#748
0#
#749
b101110011 +
1#
#750
0#
#751
b101110100 +
1#
#752
0#
#753
b101110101 +
1#
#754
0#
#755
b101110110 +
1#
#756
0#
#757
b101110111 +
1#
#758
0#
#759
b101111000 +
1#
#760
0#
#761
b101111001 +
1#
#762
0#
#763
b101111010 +
1#
#764
0#
#765
b101111011 +
1#
#766
0#
#767
b101111100 +
1#
#768
0#
#769
b101111101 +
1#
#770
0#
#771
b101111110 +
1#
#772
0#
#773
b101111111 +
1#
#774
0#
#775
b110000000 +
1#
#776
0#
#777
b110000001 +
1#
#778
0#
#779
b110000010 +
1#
#780
0#
#781
b110000011 +
1#
#782
0#
#783
b110000100 +
1#
#784
0#
#785
b110000101 +
1#
#786
0#
#787
b110000110 +
1#
#788
0#
#789
b110000111 +
1#
#790
0#
#791
b110001000 +
1#
#792
0#
#793
b110001001 +
1#
#794
0#
#795
b110001010 +
1#
#796
0#
#797
b110001011 +
1#
#798
0#
#799
b110001100 +
1#
#800
0#
#801
b110001101 +
1#
#802
0#
#803
b110001110 +
1#
#804
0#
#805
b110001111 +
1#
#806
0#
#807
b110010000 +
1#
#808
0#
#809
b110010001 +
1#
#810
0#
#811
b110010010 +
1#
#812
0#
#813
b110010011 +
1#
#814
0#
#815
b110010100 +
1#
#816
0#
#817
b110010101 +
1#
#818
0#
#819
b110010110 +
1#
#820
0#
#821
b110010111 +
1#
#822
0#
#823
b110011000 +
1#
#824
0#
#825
b110011001 +
1#
#826
0#
#827
b110011010 +
1#
#828
0#
#829
b110011011 +
1#
#830
0#
#831
b110011100 +
1#
#832
0#
#833
b110011101 +
1#
#834
0#
#835
b110011110 +
1#
#836
0#
#837
b110011111 +
1#
#838
0#
#839
b110100000 +
1#
#840
0#
#841
b110100001 +
1#
#842
0#
#843
b110100010 +
1#
#844
0#
#845
b110100011 +
1#
#846
0#
#847
b110100100 +
1#
#848
0#
#849
b110100101 +
1#
#850
0#
#851
b110100110 +
1#
#852
0#
#853
b110100111 +
1#
#854
0#
#855
b110101000 +
1#
#856
0#
#857
b110101001 +
1#
#858
0#
#859
b110101010 +
1#
#860
0#
#861
b110101011 +
1#
#862
0#
#863
b110101100 +
1#
#864
0#
#865
b110101101 +
1#
#866
0#
#867
b110101110 +
1#
#868
0#
#869
b110101111 +
1#
#870
0#
#871
b110110000 +
1#
#872
0#
#873
b11 ,
b110110001 +
1#
#874
0#
#875
b11 -
b0 +
1#
#876
0#
#877
b1 +
1#
#878
0#
#879
b10 +
1#
#880
0#
#881
b11 +
1#
#882
0#
#883
b100 +
1#
#884
0#
#885
b101 +
1#
#886
0#
#887
b110 +
1#
#888
0#
#889
b111 +
1#
#890
0#
#891
b1000 +
1#
#892
0#
#893
b1001 +
1#
#894
0#
#895
b1010 +
1#
#896
0#
#897
b1011 +
1#
#898
0#
#899
b1100 +
1#
#900
0#
#901
b1101 +
1#
#902
0#
#903
b1110 +
1#
#904
0#
#905
b1111 +
1#
#906
0#
#907
b10000 +
1#
#908
0#
#909
b10001 +
1#
#910
0#
#911
b10010 +
1#
#912
0#
#913
b10011 +
1#
#914
0#
#915
b10100 +
1#
#916
0#
#917
b10101 +
1#
#918
0#
#919
b10110 +
1#
#920
0#
#921
b10111 +
1#
#922
0#
#923
b11000 +
1#
#924
0#
#925
b11001 +
1#
#926
0#
#927
b11010 +
1#
#928
0#
#929
b11011 +
1#
#930
0#
#931
b11100 +
1#
#932
0#
#933
b11101 +
1#
#934
0#
#935
b11110 +
1#
#936
0#
#937
b11111 +
1#
#938
0#
#939
b100000 +
1#
#940
0#
#941
b100001 +
1#
#942
0#
#943
b100010 +
1#
#944
0#
#945
b100011 +
1#
#946
0#
#947
b100100 +
1#
#948
0#
#949
b100101 +
1#
#950
0#
#951
b100110 +
1#
#952
0#
#953
b100111 +
1#
#954
0#
#955
b101000 +
1#
#956
0#
#957
b101001 +
1#
#958
0#
#959
b101010 +
1#
#960
0#
#961
b101011 +
1#
#962
0#
#963
b101100 +
1#
#964
0#
#965
b101101 +
1#
#966
0#
#967
b101110 +
1#
#968
0#
#969
b101111 +
1#
#970
0#
#971
b110000 +
1#
#972
0#
#973
b110001 +
1#
#974
0#
#975
b110010 +
1#
#976
0#
#977
b110011 +
1#
#978
0#
#979
b110100 +
1#
#980
0#
#981
b110101 +
1#
#982
0#
#983
b110110 +
1#
#984
0#
#985
b110111 +
1#
#986
0#
#987
b111000 +
1#
#988
0#
#989
b111001 +
1#
#990
0#
