lab2/t1.v
module counter (
    input clk,
    input rst,
    input up_down,
    output reg [3:0] count
);

always @(posedge clk ) begin
    if (rst & ~up_down) begin
        count <= 4'b0000;
    end 
    else if (rst & up_down) begin
        count <= 4'b1111;
    end
    else if (up_down) begin
        count <= count - 1;
    end 
    else begin
        count <= count + 1;
    end
end
endmodule

lab2/t1_tb.v
`timescale 1ns/1ns
`include "t1.v"

module t1_tb;

reg rst, clk, up_down;
wire [3:0] count;

counter dut0(
    .clk(clk),
    .rst(rst),
    .up_down(up_down),
    .count(count)
);

initial begin
    $dumpfile("wave_t1.vcd");
    $dumpvars(0);
    $monitor("time=%4t,clk=%1b, rst=%1b, count=%4b",$time,clk,rst,count);
end

initial begin
    clk = 0;
    forever #5 clk = ~clk;
end

initial begin
    rst = 0;
    up_down = 0;
    #1 rst = 1;
    #10 rst = 0;
    #40 up_down = 1;
    #31 rst = 1;
    #10 rst = 0;
    #20 $finish;
end

endmodule

lab2/wave_t1.vcd
$date
	Sun May 10 16:14:52 2026
$end
$version
	Icarus Verilog
$end
$timescale
	1ns
$end
$scope module t1_tb $end
$var wire 4 ! count [3:0] $end
$var reg 1 " clk $end
$var reg 1 # rst $end
$var reg 1 $ up_down $end
$scope module dut0 $end
$var wire 1 " clk $end
$var wire 1 # rst $end
$var wire 1 $ up_down $end
$var reg 4 % count [3:0] $end
$upscope $end
$upscope $end
$enddefinitions $end
#0
$dumpvars
bx %
0$
0#
0"
bx !
$end
#1
1#
#5
b0 !
b0 %
1"
#10
0"
#11
0#
#15
b1 !
b1 %
1"
#20
0"
#25
b10 !
b10 %
1"
#30
0"
#35
b11 !
b11 %
1"
#40
0"
#45
b100 !
b100 %
1"
#50
0"
#51
1$
#55
b11 !
b11 %
1"
#60
0"
#65
b10 !
b10 %
1"
#70
0"
#75
b1 !
b1 %
1"
#80
0"
#82
1#
#85
b1111 !
b1111 %
1"
#90
0"
#92
0#
#95
b1110 !
b1110 %
1"
#100
0"
#105
b1101 !
b1101 %
1"
