lab2/t2.v
module gray(
    input rst,clk,
    output wire [15:0] gray_out
);
reg[15:0] counter;
always @(posedge clk) begin
    if (rst) begin
        counter <= 0;
    end 
    else begin
        counter <= counter + 1;
    end
end

assign gray_out = counter ^ (counter >> 1);

endmodule

lab2/t2_tb.v
`timescale 1ns/1ns
`include "t2.v"

module t2_tb;

reg rst, clk;
wire [15:0] gray_out;

gray dut0(
    .clk(clk),
    .rst(rst),
    .gray_out(gray_out)
);

initial begin
    $dumpfile("wave_t2.vcd");
    $dumpvars(0);
    $monitor("time=%4t,clk=%1b, rst=%1b, gray_out=%4b",$time,clk,rst,gray_out);
end

initial begin
    clk = 0;
    forever #5 clk = ~clk;
end

initial begin
    rst = 0;
    #1 rst = 1;
    #10 rst = 0;
    #60 $finish;
end

endmodule

lab2/wave_t2.vcd
$date
	Sun May 10 16:51:38 2026
$end
$version
	Icarus Verilog
$end
$timescale
	1ns
$end
$scope module t2_tb $end
$var wire 16 ! gray_out [15:0] $end
$var reg 1 " clk $end
$var reg 1 # rst $end
$scope module dut0 $end
$var wire 1 " clk $end
$var wire 16 $ gray_out [15:0] $end
$var wire 1 # rst $end
$var reg 16 % counter [15:0] $end
$upscope $end
$upscope $end
$enddefinitions $end
#0
$dumpvars
bx %
bx $
0#
0"
bx !
$end
#1
1#
#5
b0 !
b0 $
b0 %
1"
#10
0"
#11
0#
#15
b1 !
b1 $
b1 %
1"
#20
0"
#25
b11 !
b11 $
b10 %
1"
#30
0"
#35
b10 !
b10 $
b11 %
1"
#40
0"
#45
b110 !
b110 $
b100 %
1"
#50
0"
#55
b111 !
b111 $
b101 %
1"
#60
0"
#65
b101 !
b101 $
b110 %
1"
