t4.v
module test;

reg [3:0] counter;
reg rst;
reg clk;
wire [1:0] led;

initial clk = 0;
always #1 clk = ~clk;

initial begin
    rst = 0;
    #10 rst = 1;
    #10 counter = 4'd8;
    #10 rst = 0;
    #100 $finish;
end

initial begin
    $monitor(counter);
end

always @(posedge clk) begin
    counter <= counter + 1 + led;
end

assign led = counter[1]+1;

initial begin
    $dumpfile("wave_t4.vcd"); 
    $dumpvars(0);       
end

endmodule

lab3/wave_t4.vcd
$date
	Sun May 10 22:34:14 2026
$end
$version
	Icarus Verilog
$end
$timescale
	1s
$end
$scope module test $end
$var wire 2 ! led [1:0] $end
$var reg 1 " clk $end
$var reg 4 # counter [3:0] $end
$var reg 1 $ rst $end
$upscope $end
$enddefinitions $end
#0
$dumpvars
0$
bx #
0"
bx !
$end
#1
1"
#2
0"
#3
1"
#4
0"
#5
1"
#6
0"
#7
1"
#8
0"
#9
1"
#10
0"
1$
#11
1"
#12
0"
#13
1"
#14
0"
#15
1"
#16
0"
#17
1"
#18
0"
#19
1"
#20
b1 !
0"
b1000 #
#21
b10 !
b1010 #
1"
#22
0"
#23
b1 !
b1101 #
1"
#24
0"
#25
b10 !
b1111 #
1"
#26
0"
#27
b10 #
1"
#28
0"
#29
b1 !
b101 #
1"
#30
0"
0$
#31
b10 !
b111 #
1"
#32
0"
#33
b1010 #
1"
#34
0"
#35
b1 !
b1101 #
1"
#36
0"
#37
b10 !
b1111 #
1"
#38
0"
#39
b10 #
1"
#40
0"
#41
b1 !
b101 #
1"
#42
0"
#43
b10 !
b111 #
1"
#44
0"
#45
b1010 #
1"
#46
0"
#47
b1 !
b1101 #
1"
#48
0"
#49
b10 !
b1111 #
1"
#50
0"
#51
b10 #
1"
#52
0"
#53
b1 !
b101 #
1"
#54
0"
#55
b10 !
b111 #
1"
#56
0"
#57
b1010 #
1"
#58
0"
#59
b1 !
b1101 #
1"
#60
0"
#61
b10 !
b1111 #
1"
#62
0"
#63
b10 #
1"
#64
0"
#65
b1 !
b101 #
1"
#66
0"
#67
b10 !
b111 #
1"
#68
0"
#69
b1010 #
1"
#70
0"
#71
b1 !
b1101 #
1"
#72
0"
#73
b10 !
b1111 #
1"
#74
0"
#75
b10 #
1"
#76
0"
#77
b1 !
b101 #
1"
#78
0"
#79
b10 !
b111 #
1"
#80
0"
#81
b1010 #
1"
#82
0"
#83
b1 !
b1101 #
1"
#84
0"
#85
b10 !
b1111 #
1"
#86
0"
#87
b10 #
1"
#88
0"
#89
b1 !
b101 #
1"
#90
0"
#91
b10 !
b111 #
1"
#92
0"
#93
b1010 #
1"
#94
0"
#95
b1 !
b1101 #
1"
#96
0"
#97
b10 !
b1111 #
1"
#98
0"
#99
b10 #
1"
#100
0"
#101
b1 !
b101 #
1"
#102
0"
#103
b10 !
b111 #
1"
#104
0"
#105
b1010 #
1"
#106
0"
#107
b1 !
b1101 #
1"
#108
0"
#109
b10 !
b1111 #
1"
#110
0"
#111
b10 #
1"
#112
0"
#113
b1 !
b101 #
1"
#114
0"
#115
b10 !
b111 #
1"
#116
0"
#117
b1010 #
1"
#118
0"
#119
b1 !
b1101 #
1"
#120
0"
#121
b10 !
b1111 #
1"
#122
0"
#123
b10 #
1"
#124
0"
#125
b1 !
b101 #
1"
#126
0"
#127
b10 !
b111 #
1"
#128
0"
#129
b1010 #
1"
