lab3/t2.v
module test;

reg [7:0] counter;
reg rst;
reg clk;

initial clk = 0;
always #1 clk = ~clk;

initial begin
    rst = 0;
    #11 rst = 1;
    #10 rst = 0;
    #100 $finish;
end

initial begin
    $monitor("time=%0t counter=%0d", $time, counter);
end


always @(posedge clk or posedge rst) begin
    if (rst) begin
        counter <= 0;
    end 
    else begin
    counter <= counter + 1;
    end
end

initial begin
    $dumpfile("wave_t2.vcd"); 
    $dumpvars(0);       
end

endmodule

lab3/wave_t2.vcd
$date
	Sun May 10 21:58:12 2026
$end
$version
	Icarus Verilog
$end
$timescale
	1s
$end
$scope module test $end
$var reg 1 ! clk $end
$var reg 8 " counter [7:0] $end
$var reg 1 # rst $end
$upscope $end
$enddefinitions $end
#0
$dumpvars
0#
bx "
0!
$end
#1
1!
#2
0!
#3
1!
#4
0!
#5
1!
#6
0!
#7
1!
#8
0!
#9
1!
#10
0!
#11
b0 "
1!
1#
#12
0!
#13
1!
#14
0!
#15
1!
#16
0!
#17
1!
#18
0!
#19
1!
#20
0!
#21
b1 "
1!
0#
#22
0!
#23
b10 "
1!
#24
0!
#25
b11 "
1!
#26
0!
#27
b100 "
1!
#28
0!
#29
b101 "
1!
#30
0!
#31
b110 "
1!
#32
0!
#33
b111 "
1!
#34
0!
#35
b1000 "
1!
#36
0!
#37
b1001 "
1!
#38
0!
#39
b1010 "
1!
#40
0!
#41
b1011 "
1!
#42
0!
#43
b1100 "
1!
#44
0!
#45
b1101 "
1!
#46
0!
#47
b1110 "
1!
#48
0!
#49
b1111 "
1!
#50
0!
#51
b10000 "
1!
#52
0!
#53
b10001 "
1!
#54
0!
#55
b10010 "
1!
#56
0!
#57
b10011 "
1!
#58
0!
#59
b10100 "
1!
#60
0!
#61
b10101 "
1!
#62
0!
#63
b10110 "
1!
#64
0!
#65
b10111 "
1!
#66
0!
#67
b11000 "
1!
#68
0!
#69
b11001 "
1!
#70
0!
#71
b11010 "
1!
#72
0!
#73
b11011 "
1!
#74
0!
#75
b11100 "
1!
#76
0!
#77
b11101 "
1!
#78
0!
#79
b11110 "
1!
#80
0!
#81
b11111 "
1!
#82
0!
#83
b100000 "
1!
#84
0!
#85
b100001 "
1!
#86
0!
#87
b100010 "
1!
#88
0!
#89
b100011 "
1!
#90
0!
#91
b100100 "
1!
#92
0!
#93
b100101 "
1!
#94
0!
#95
b100110 "
1!
#96
0!
#97
b100111 "
1!
#98
0!
#99
b101000 "
1!
#100
0!
#101
b101001 "
1!
#102
0!
#103
b101010 "
1!
#104
0!
#105
b101011 "
1!
#106
0!
#107
b101100 "
1!
#108
0!
#109
b101101 "
1!
#110
0!
#111
b101110 "
1!
#112
0!
#113
b101111 "
1!
#114
0!
#115
b110000 "
1!
#116
0!
#117
b110001 "
1!
#118
0!
#119
b110010 "
1!
#120
0!
#121
b110011 "
1!
