lab3/t1.v
module test1;

reg en;
reg [7:0] a1,b1,i1;
reg clk;

initial clk = 0;
always #1 clk = ~clk;

initial begin
    a1 = 0;
    b1 = 0;
    i1 = 0;
    en = 1;
    #100 $finish;
end

initial begin
    $monitor("Module1 (Non-Blocking): a=%d, b=%d, i=%d", a1, b1, i1);
    
end

always @(posedge clk) begin
if(i1<=8'd16) begin
    i1 <= i1+1; 
    a1 <= i1;
    b1 <= a1;
end
end

endmodule

module test2;

reg en;
reg [7:0] a2,b2,i2;
reg clk;

initial clk = 0;
always #1 clk = ~clk;

initial begin
    a2 = 0;
    b2 = 0;
    i2 = 0;
    en = 1;
    #100 $finish;
end

initial begin
    $monitor("Module2 (Blocking): a=%d, b=%d, i=%d", a2, b2, i2);
    
end

always @(posedge clk) begin
if(i2<=8'd16) begin
//与程序1唯一的不同：换成了阻塞赋值
    i2 = i2+1;
    a2 = i2;
    b2 = a2;
end
end

initial begin
    $dumpfile("wave_t1.vcd"); 
    $dumpvars(0);       
end

endmodule

lab3/wave_t3.vcd
$date
	Sun May 10 22:09:09 2026
$end
$version
	Icarus Verilog
$end
$timescale
	1s
$end
$scope module test1 $end
$var reg 8 ! a1 [7:0] $end
$var reg 8 " b1 [7:0] $end
$var reg 1 # clk $end
$var reg 1 $ en $end
$var reg 8 % i1 [7:0] $end
$upscope $end
$scope module test2 $end
$var reg 8 & a2 [7:0] $end
$var reg 8 ' b2 [7:0] $end
$var reg 1 ( clk $end
$var reg 1 ) en $end
$var reg 8 * i2 [7:0] $end
$upscope $end
$enddefinitions $end
#0
$dumpvars
b0 *
1)
0(
b0 '
b0 &
b0 %
1$
0#
b0 "
b0 !
$end
#1
b10 '
b1 &
b1 *
b1 !
b1 "
b1 %
1(
1#
#2
0(
0#
#3
b11 '
b10 &
b10 *
b10 !
b10 "
b10 %
1(
1#
#4
0(
0#
#5
b100 '
b11 &
b11 *
b11 !
b11 "
b11 %
1(
1#
#6
0(
0#
#7
b101 '
b100 &
b100 *
b100 !
b100 "
b100 %
1(
1#
#8
0(
0#
#9
b110 '
b101 &
b101 *
b101 !
b101 "
b101 %
1(
1#
#10
0(
0#
#11
b111 '
b110 &
b110 *
b110 !
b110 "
b110 %
1(
1#
#12
0(
0#
#13
b1000 '
b111 &
b111 *
b111 !
b111 "
b111 %
1(
1#
#14
0(
0#
#15
b1001 '
b1000 &
b1000 *
b1000 !
b1000 "
b1000 %
1(
1#
#16
0(
0#
#17
b1010 '
b1001 &
b1001 *
b1001 !
b1001 "
b1001 %
1(
1#
#18
0(
0#
#19
b1011 '
b1010 &
b1010 *
b1010 !
b1010 "
b1010 %
1(
1#
#20
0(
0#
#21
b1100 '
b1011 &
b1011 *
b1011 !
b1011 "
b1011 %
1(
1#
#22
0(
0#
#23
b1101 '
b1100 &
b1100 *
b1100 !
b1100 "
b1100 %
1(
1#
#24
0(
0#
#25
b1110 '
b1101 &
b1101 *
b1101 !
b1101 "
b1101 %
1(
1#
#26
0(
0#
#27
b1111 '
b1110 &
b1110 *
b1110 !
b1110 "
b1110 %
1(
1#
#28
0(
0#
#29
b10000 '
b1111 &
b1111 *
b1111 !
b1111 "
b1111 %
1(
1#
#30
0(
0#
#31
b10001 '
b10000 &
b10000 *
b10000 !
b10000 "
b10000 %
1(
1#
#32
0(
0#
#33
b10010 '
b10001 &
b10001 *
b10001 !
b10001 "
b10001 %
1(
1#
