lab6/RAM_sync.v
module ram_sr # 
(parameter DATA_WIDTH = 8, ADDR_WIDTH = 8)
(
clk         , // Clock Input
address     , // Address Input
d           , // Data input
q           , // Data output
cs          , // Chip Select
web         , // Write Enable/Read Enable, low active
oe            // Output Enable
); 

localparam RAM_DEPTH = 1 << ADDR_WIDTH;

//--------------Input Ports----------------------- 
input clk;
input [ADDR_WIDTH-1:0] address;
input cs;
input web;
input oe; 

//--------------Inout Ports----------------------- 
input [DATA_WIDTH-1:0]  d;
output [DATA_WIDTH-1:0]  q;

//--------------Internal variables---------------- 
reg [DATA_WIDTH-1:0] data_out;
reg [DATA_WIDTH-1:0] mem [0:RAM_DEPTH-1];

//--------------Core Function--------------------- 
// Tri-State Buffer control 
// output : When web = 1, oe = 1, cs = 1
assign q = (cs && oe && web) ? data_out : 'bz; 

// Memory Write Block 
// Write Operation : When web = 0, cs = 1
always @ (posedge clk)
begin : MEM_WRITE
   if ( cs && ~web ) begin
       mem[address] = d;
   end
end

// Memory Read Block 
// Read Operation : When web = 1, oe = 1, cs = 1
always @ (posedge clk)
begin : MEM_READ
    if (cs && web && oe) begin
         data_out = mem[address];
    end
end

endmodule

lab6/RAM_async.v
module ram_ar # 
(parameter DATA_WIDTH = 8, ADDR_WIDTH = 8)
(
clk         , // Clock Input
address     , // Address Input
d           , // Data input
q           , // Data output
cs          , // Chip Select
web         , // Write Enable/Read Enable, low active
oe            // Output Enable
); 

localparam RAM_DEPTH = 1 << ADDR_WIDTH;

//--------------Input Ports----------------------- 
input clk;
input [ADDR_WIDTH-1:0] address;
input cs;
input web;
input oe; 

//--------------Inout Ports----------------------- 
input [DATA_WIDTH-1:0]  d;
output [DATA_WIDTH-1:0]  q;

//--------------Internal variables---------------- 
reg [DATA_WIDTH-1:0] data_out;
reg [DATA_WIDTH-1:0] mem [0:RAM_DEPTH-1];

//--------------Core Function--------------------- 
// Tri-State Buffer control 
// output : When web = 1, oe = 1, cs = 1
assign q = (cs && oe && web) ? data_out : 'bz; 

// Memory Write Block 
// Write Operation : When web = 0, cs = 1
always @ (posedge clk)
begin : MEM_WRITE
   if ( cs && ~web ) begin
       mem[address] = d;
   end
end

// Memory Read Block 
// Read Operation : When web = 1, oe = 1, cs = 1
always @ (address or cs or web or oe)
begin : MEM_READ
    if (cs && web && oe) begin
         data_out = mem[address];
    end
end

endmodule

lab6/RAM_tb.v
`timescale 1ns/1ns
`include "RAM_async.v"
`include "RAM_sync.v"
module tb;

reg clk;
reg [7:0] addr;
reg [15:0] d;
reg cs;
reg web;
reg oe;
wire [15:0] q_ar;
wire [15:0] q_sr;
integer i;

initial begin
    $dumpfile("wave_RAM.vcd");
    $dumpvars(0);
    $monitor("time=%4t, clk=%1b, web=%1b, d=%2h, q_ar=%2h, q_sr=%2h",$time,clk,web,d,q_ar,q_sr);
end

initial
begin
    clk = 0;
    forever #1 clk = ~clk;
end

initial
begin
    cs = 1;
    oe = 1;
    // test write
    for(i=0;i<(1<<4);i=i+1) begin
        #2 web=0;
        addr = i;
        d = i;
    end
    // test read
    for(i=0;i<(1<<4);i=i+1) begin
        #2 web=1;
        addr = i;
        d = $random;
    end

    #10 $finish;
end

// Async read RAM
ram_ar #(.DATA_WIDTH(16), .ADDR_WIDTH(8)) u0 (
    .clk( clk )
    ,.address ( addr )
    ,.d  ( d )
    ,.q ( q_ar )
    ,.cs ( cs )
    ,.web ( web )
    ,.oe ( oe )
); 

// Sync read RAM
ram_sr #(.DATA_WIDTH(16), .ADDR_WIDTH(8)) u1 (
    .clk( clk )
    ,.address ( addr )
    ,.d  ( d )
    ,.q ( q_sr )
    ,.cs ( cs )
    ,.web ( web )
    ,.oe ( oe )
);

endmodule

lab6/wave.vcd
$date
	Wed May 27 19:37:03 2026
$end
$version
	Icarus Verilog
$end
$timescale
	1ns
$end
$scope module tb $end
$var wire 16 ! q_sr [15:0] $end
$var wire 16 " q_ar [15:0] $end
$var reg 8 # addr [7:0] $end
$var reg 1 $ clk $end
$var reg 1 % cs $end
$var reg 16 & d [15:0] $end
$var reg 1 ' oe $end
$var reg 1 ( web $end
$var integer 32 ) i [31:0] $end
$scope module u0 $end
$var wire 8 * address [7:0] $end
$var wire 1 $ clk $end
$var wire 1 % cs $end
$var wire 16 + d [15:0] $end
$var wire 1 ' oe $end
$var wire 1 ( web $end
$var wire 16 , q [15:0] $end
$var reg 16 - data_out [15:0] $end
$scope begin MEM_READ $end
$upscope $end
$scope begin MEM_WRITE $end
$upscope $end
$upscope $end
$scope module u1 $end
$var wire 8 . address [7:0] $end
$var wire 1 $ clk $end
$var wire 1 % cs $end
$var wire 16 / d [15:0] $end
$var wire 1 ' oe $end
$var wire 1 ( web $end
$var wire 16 0 q [15:0] $end
$var reg 16 1 data_out [15:0] $end
$scope begin MEM_READ $end
$upscope $end
$scope begin MEM_WRITE $end
$upscope $end
$upscope $end
$upscope $end
$enddefinitions $end
#0
$dumpvars
bx 1
bx 0
bx /
bx .
bx -
bx ,
bx +
bx *
b0 )
x(
1'
bx &
1%
0$
bx #
bx "
bx !
$end
#1
1$
#2
bz "
bz ,
bz !
bz 0
0$
b1 )
b0 &
b0 +
b0 /
b0 #
b0 *
b0 .
0(
#3
1$
#4
0$
b10 )
b1 &
b1 +
b1 /
b1 #
b1 *
b1 .
#5
1$
#6
0$
b11 )
b10 &
b10 +
b10 /
b10 #
b10 *
b10 .
#7
1$
#8
0$
b100 )
b11 &
b11 +
b11 /
b11 #
b11 *
b11 .
#9
1$
#10
0$
b101 )
b100 &
b100 +
b100 /
b100 #
b100 *
b100 .
#11
1$
#12
0$
b110 )
b101 &
b101 +
b101 /
b101 #
b101 *
b101 .
#13
1$
#14
0$
b111 )
b110 &
b110 +
b110 /
b110 #
b110 *
b110 .
#15
1$
#16
0$
b1000 )
b111 &
b111 +
b111 /
b111 #
b111 *
b111 .
#17
1$
#18
0$
b1001 )
b1000 &
b1000 +
b1000 /
b1000 #
b1000 *
b1000 .
#19
1$
#20
0$
b1010 )
b1001 &
b1001 +
b1001 /
b1001 #
b1001 *
b1001 .
#21
1$
#22
0$
b1011 )
b1010 &
b1010 +
b1010 /
b1010 #
b1010 *
b1010 .
#23
1$
#24
0$
b1100 )
b1011 &
b1011 +
b1011 /
b1011 #
b1011 *
b1011 .
#25
1$
#26
0$
b1101 )
b1100 &
b1100 +
b1100 /
b1100 #
b1100 *
b1100 .
#27
1$
#28
0$
b1110 )
b1101 &
b1101 +
b1101 /
b1101 #
b1101 *
b1101 .
#29
1$
#30
0$
b1111 )
b1110 &
b1110 +
b1110 /
b1110 #
b1110 *
b1110 .
#31
1$
#32
0$
b0 )
b1111 &
b1111 +
b1111 /
b1111 #
b1111 *
b1111 .
#33
1$
#34
b0 "
b0 ,
bx !
bx 0
b0 -
0$
b1 )
b11010100100100 &
b11010100100100 +
b11010100100100 /
b0 #
b0 *
b0 .
1(
#35
b0 !
b0 0
b0 1
1$
#36
b1 "
b1 ,
b1 -
0$
b10 )
b101111010000001 &
b101111010000001 +
b101111010000001 /
b1 #
b1 *
b1 .
#37
b1 !
b1 0
b1 1
1$
#38
b10 "
b10 ,
b10 -
0$
b11 )
b1101011000001001 &
b1101011000001001 +
b1101011000001001 /
b10 #
b10 *
b10 .
#39
b10 !
b10 0
b10 1
1$
#40
b11 "
b11 ,
b11 -
0$
b100 )
b101011001100011 &
b101011001100011 +
b101011001100011 /
b11 #
b11 *
b11 .
#41
b11 !
b11 0
b11 1
1$
#42
b100 "
b100 ,
b100 -
0$
b101 )
b111101100001101 &
b111101100001101 +
b111101100001101 /
b100 #
b100 *
b100 .
#43
b100 !
b100 0
b100 1
1$
#44
b101 "
b101 ,
b101 -
0$
b110 )
b1001100110001101 &
b1001100110001101 +
b1001100110001101 /
b101 #
b101 *
b101 .
#45
b101 !
b101 0
b101 1
1$
#46
b110 "
b110 ,
b110 -
0$
b111 )
b1000010001100101 &
b1000010001100101 +
b1000010001100101 /
b110 #
b110 *
b110 .
#47
b110 !
b110 0
b110 1
1$
#48
b111 "
b111 ,
b111 -
0$
b1000 )
b101001000010010 &
b101001000010010 +
b101001000010010 /
b111 #
b111 *
b111 .
#49
b111 !
b111 0
b111 1
1$
#50
b1000 "
b1000 ,
b1000 -
0$
b1001 )
b1110001100000001 &
b1110001100000001 +
b1110001100000001 /
b1000 #
b1000 *
b1000 .
#51
b1000 !
b1000 0
b1000 1
1$
#52
b1001 "
b1001 ,
b1001 -
0$
b1010 )
b1100110100001101 &
b1100110100001101 +
b1100110100001101 /
b1001 #
b1001 *
b1001 .
#53
b1001 !
b1001 0
b1001 1
1$
#54
b1010 "
b1010 ,
b1010 -
0$
b1011 )
b1111000101110110 &
b1111000101110110 +
b1111000101110110 /
b1010 #
b1010 *
b1010 .
#55
b1010 !
b1010 0
b1010 1
1$
#56
b1011 "
b1011 ,
b1011 -
0$
b1100 )
b1100110100111101 &
b1100110100111101 +
b1100110100111101 /
b1011 #
b1011 *
b1011 .
#57
b1011 !
b1011 0
b1011 1
1$
#58
b1100 "
b1100 ,
b1100 -
0$
b1101 )
b101011111101101 &
b101011111101101 +
b101011111101101 /
b1100 #
b1100 *
b1100 .
#59
b1100 !
b1100 0
b1100 1
1$
#60
b1101 "
b1101 ,
b1101 -
0$
b1110 )
b1111011110001100 &
b1111011110001100 +
b1111011110001100 /
b1101 #
b1101 *
b1101 .
#61
b1101 !
b1101 0
b1101 1
1$
#62
b1110 "
b1110 ,
b1110 -
0$
b1111 )
b1110100111111001 &
b1110100111111001 +
b1110100111111001 /
b1110 #
b1110 *
b1110 .
#63
b1110 !
b1110 0
b1110 1
1$
#64
b1111 "
b1111 ,
b1111 -
0$
b10000 )
b10010011000110 &
b10010011000110 +
b10010011000110 /
b1111 #
b1111 *
b1111 .
#65
b1111 !
b1111 0
b1111 1
1$
