lab6/RAM_sync.v
module ram_sr # 
(parameter DATA_WIDTH = 8, ADDR_WIDTH = 8)
(
clk         , // Clock Input
address     , // Address Input
d           , // Data input
q           , // Data output
cs          , // Chip Select
web         , // Write Enable/Read Enable, low active
oe            // Output Enable
); 

localparam RAM_DEPTH = 1 << ADDR_WIDTH;

//--------------Input Ports----------------------- 
input clk;
input [ADDR_WIDTH-1:0] address;
input cs;
input web;
input oe; 

//--------------Inout Ports----------------------- 
input [DATA_WIDTH-1:0]  d;
output [DATA_WIDTH-1:0]  q;

//--------------Internal variables---------------- 
reg [DATA_WIDTH-1:0] data_out;
reg [DATA_WIDTH-1:0] mem [0:RAM_DEPTH-1];

//--------------Core Function--------------------- 
// Tri-State Buffer control 
// output : When web = 1, oe = 1, cs = 1
assign q = (cs && oe && web) ? data_out : 'bz; 

// Memory Write Block 
// Write Operation : When web = 0, cs = 1
always @ (posedge clk)
begin : MEM_WRITE
   if ( cs && ~web ) begin
       mem[address] = d;
   end
end

// Memory Read Block 
// Read Operation : When web = 1, oe = 1, cs = 1
always @ (posedge clk)
begin : MEM_READ
    if (cs && web && oe) begin
         data_out = mem[address];
    end
end

endmodule

lab6/FIFO.v
module fifo (
input   clk             , // Clock input
input   rstb            , // Reset all function, low active
input   rd              , // Pop one datum out
input   wr              , // Push one datum in
input   [15:0] data_in  , // Data input port
output  [15:0] data_out , // Data output port
output  empty           , // FIFO empty indicator, high active
output  full              // FIFO full indicator, low active
);  

	localparam ADDR_WIDTH = 8;
	localparam DEPTH = 1 << ADDR_WIDTH;

	reg [ADDR_WIDTH-1:0] wr_addr;
	reg [ADDR_WIDTH-1:0] rd_addr;
	reg [ADDR_WIDTH:0] count;

	localparam [ADDR_WIDTH-1:0] LAST_ADDR = DEPTH - 1;
	reg [ADDR_WIDTH-1:0] ram_addr;
	reg web;
	wire cs;
	reg oe;

	assign empty = (count == 0);
	assign full = (count == DEPTH);

	wire rd_en = rd && !empty;
    wire wr_en = wr && !full;

	assign cs = 1'b1;


	always @* begin
		ram_addr = rd_addr;
		web = 1'b1;
		if (wr_en) begin
			ram_addr = wr_addr;
			web = 1'b0;
		end else if (rd_en) begin
			ram_addr = rd_addr;
			web = 1'b1;
		end
	end

	ram_sr #(.DATA_WIDTH(16), .ADDR_WIDTH(ADDR_WIDTH)) u_ram (
		.clk( clk )
		,.address ( ram_addr )
		,.d  ( data_in )
		,.q ( data_out )
		,.cs ( cs )
		,.web ( web )
		,.oe ( oe )
	);

	always @(posedge clk) begin
        oe <= rd_en;
		if (!rstb) begin
			wr_addr <= {ADDR_WIDTH{1'b0}};
			rd_addr <= {ADDR_WIDTH{1'b0}};
			count <= {ADDR_WIDTH+1{1'b0}};
		end else begin
			if (wr_en) begin
				wr_addr <= (wr_addr == LAST_ADDR) ? {ADDR_WIDTH{1'b0}} : (wr_addr + 1'b1);
				count <= count + 1'b1;
			end else if (rd_en) begin
				rd_addr <= (rd_addr == LAST_ADDR) ? {ADDR_WIDTH{1'b0}} : (rd_addr + 1'b1);
				count <= count - 1'b1;
			end
	end
    end
endmodule

lab6/FIFO_tb.v
`timescale 1ns/1ns
`include "FIFO.v"
`include "RAM_sync.v"
module fifo_tb;
	reg clk;
	reg rstb;
	reg rd;
	reg wr;
	reg [15:0] data_in;
	wire [15:0] data_out;
	wire empty;
	wire full;

	fifo dut (
		.clk(clk),
		.rstb(rstb),
		.rd(rd),
		.wr(wr),
		.data_in(data_in),
		.data_out(data_out),
		.empty(empty),
		.full(full)
	);

	initial begin
		$dumpfile("wave_fifo.vcd");
		$dumpvars(0);
	end

	initial begin
		clk = 1'b0;
		forever #5 clk = ~clk;
	end

	integer i;
	initial begin
		rstb = 1'b0;
		rd = 1'b0;
		wr = 1'b0;
		data_in = 16'h0000;

		repeat (2) @(posedge clk);
		rstb = 1'b1;

		for (i = 0; i < 16; i = i + 1) begin
			@(negedge clk);
			wr = 1'b1;
			rd = 1'b0;
			data_in = i[15:0];
		end
		@(negedge clk);
		wr = 1'b0;

		for (i = 0; i < 4; i = i + 1) begin
			@(negedge clk);
			rd = 1'b1;
			wr = 1'b0;
		end
		@(negedge clk);
		rd = 1'b0;

		for (i = 0; i < 15; i = i + 1) begin
			@(negedge clk);
			rd = 1'b1;
		end
		@(negedge clk);
		rd = 1'b0;

		#20;
		$finish;
	end
endmodule

lab6/wave_fifo.vcd
$date
	Wed May 27 22:14:32 2026
$end
$version
	Icarus Verilog
$end
$timescale
	1ns
$end
$scope module fifo_tb $end
$var wire 1 ! full $end
$var wire 1 " empty $end
$var wire 16 # data_out [15:0] $end
$var reg 1 $ clk $end
$var reg 16 % data_in [15:0] $end
$var reg 1 & rd $end
$var reg 1 ' rstb $end
$var reg 1 ( wr $end
$var integer 32 ) i [31:0] $end
$scope module dut $end
$var wire 1 $ clk $end
$var wire 1 * cs $end
$var wire 16 + data_in [15:0] $end
$var wire 1 & rd $end
$var wire 1 , rd_en $end
$var wire 1 ' rstb $end
$var wire 1 ( wr $end
$var wire 1 - wr_en $end
$var wire 1 ! full $end
$var wire 1 " empty $end
$var wire 16 . data_out [15:0] $end
$var reg 9 / count [8:0] $end
$var reg 1 0 oe $end
$var reg 8 1 ram_addr [7:0] $end
$var reg 8 2 rd_addr [7:0] $end
$var reg 1 3 web $end
$var reg 8 4 wr_addr [7:0] $end
$scope module u_ram $end
$var wire 8 5 address [7:0] $end
$var wire 1 $ clk $end
$var wire 1 * cs $end
$var wire 16 6 d [15:0] $end
$var wire 1 0 oe $end
$var wire 1 3 web $end
$var wire 16 7 q [15:0] $end
$var reg 16 8 data_out [15:0] $end
$scope begin MEM_READ $end
$upscope $end
$scope begin MEM_WRITE $end
$upscope $end
$upscope $end
$upscope $end
$upscope $end
$enddefinitions $end
#0
$dumpvars
bx 8
bx 7
b0 6
bx 5
bx 4
13
bx 2
bx 1
x0
bx /
bx .
0-
0,
b0 +
1*
bx )
0(
0'
0&
b0 %
0$
bx #
x"
x!
$end
#5
bz #
bz .
bz 7
b0 1
b0 5
1"
0!
b0 /
b0 2
b0 4
00
1$
#10
0$
#15
b0 )
1'
1$
#20
03
1-
b1 )
1(
0$
#25
b1 1
b1 5
03
0"
b1 /
b1 4
1$
#30
b10 )
b1 %
b1 +
b1 6
0$
#35
03
b10 1
b10 5
b10 /
b10 4
1$
#40
b11 )
b10 %
b10 +
b10 6
0$
#45
03
b11 1
b11 5
b11 /
b11 4
1$
#50
b100 )
b11 %
b11 +
b11 6
0$
#55
03
b100 1
b100 5
b100 /
b100 4
1$
#60
b101 )
b100 %
b100 +
b100 6
0$
#65
03
b101 1
b101 5
b101 /
b101 4
1$
#70
b110 )
b101 %
b101 +
b101 6
0$
#75
03
b110 1
b110 5
b110 /
b110 4
1$
#80
b111 )
b110 %
b110 +
b110 6
0$
#85
03
b111 1
b111 5
b111 /
b111 4
1$
#90
b1000 )
b111 %
b111 +
b111 6
0$
#95
03
b1000 1
b1000 5
b1000 /
b1000 4
1$
#100
b1001 )
b1000 %
b1000 +
b1000 6
0$
#105
03
b1001 1
b1001 5
b1001 /
b1001 4
1$
#110
b1010 )
b1001 %
b1001 +
b1001 6
0$
#115
03
b1010 1
b1010 5
b1010 /
b1010 4
1$
#120
b1011 )
b1010 %
b1010 +
b1010 6
0$
#125
03
b1011 1
b1011 5
b1011 /
b1011 4
1$
#130
b1100 )
b1011 %
b1011 +
b1011 6
0$
#135
03
b1100 1
b1100 5
b1100 /
b1100 4
1$
#140
b1101 )
b1100 %
b1100 +
b1100 6
0$
#145
03
b1101 1
b1101 5
b1101 /
b1101 4
1$
#150
b1110 )
b1101 %
b1101 +
b1101 6
0$
#155
03
b1110 1
b1110 5
b1110 /
b1110 4
1$
#160
b1111 )
b1110 %
b1110 +
b1110 6
0$
#165
03
b1111 1
b1111 5
b1111 /
b1111 4
1$
#170
b10000 )
b1111 %
b1111 +
b1111 6
0$
#175
03
b10000 1
b10000 5
b10000 /
b10000 4
1$
#180
13
b0 1
b0 5
0-
b0 )
0(
0$
#185
1$
#190
1,
b1 )
1&
0$
#195
bx #
bx .
bx 7
b1 1
b1 5
b1111 /
b1 2
10
1$
#200
b10 )
0$
#205
b10 1
b10 5
b1110 /
b10 2
b1 #
b1 .
b1 7
b1 8
1$
#210
b11 )
0$
#215
b11 1
b11 5
b1101 /
b11 2
b10 #
b10 .
b10 7
b10 8
1$
#220
b100 )
0$
#225
b100 1
b100 5
b1100 /
b100 2
b11 #
b11 .
b11 7
b11 8
1$
#230
0,
b0 )
0&
0$
#235
00
bz #
bz .
bz 7
b100 8
1$
#240
1,
b1 )
1&
0$
#245
b100 #
b100 .
b100 7
b101 1
b101 5
b1011 /
b101 2
10
1$
#250
b10 )
0$
#255
b110 1
b110 5
b1010 /
b110 2
b101 #
b101 .
b101 7
b101 8
1$
#260
b11 )
0$
#265
b111 1
b111 5
b1001 /
b111 2
b110 #
b110 .
b110 7
b110 8
1$
#270
b100 )
0$
#275
b1000 1
b1000 5
b1000 /
b1000 2
b111 #
b111 .
b111 7
b111 8
1$
#280
b101 )
0$
#285
b1001 1
b1001 5
b111 /
b1001 2
b1000 #
b1000 .
b1000 7
b1000 8
1$
#290
b110 )
0$
#295
b1010 1
b1010 5
b110 /
b1010 2
b1001 #
b1001 .
b1001 7
b1001 8
1$
#300
b111 )
0$
#305
b1011 1
b1011 5
b101 /
b1011 2
b1010 #
b1010 .
b1010 7
b1010 8
1$
#310
b1000 )
0$
#315
b1100 1
b1100 5
b100 /
b1100 2
b1011 #
b1011 .
b1011 7
b1011 8
1$
#320
b1001 )
0$
#325
b1101 1
b1101 5
b11 /
b1101 2
b1100 #
b1100 .
b1100 7
b1100 8
1$
#330
b1010 )
0$
#335
b1110 1
b1110 5
b10 /
b1110 2
b1101 #
b1101 .
b1101 7
b1101 8
1$
#340
b1011 )
0$
#345
b1111 1
b1111 5
b1 /
b1111 2
b1110 #
b1110 .
b1110 7
b1110 8
1$
#350
b1100 )
0$
#355
0,
b10000 1
b10000 5
1"
b0 /
b10000 2
b1111 #
b1111 .
b1111 7
b1111 8
1$
#360
b1101 )
0$
#365
00
bz #
bz .
bz 7
bx 8
1$
#370
b1110 )
0$
#375
1$
#380
b1111 )
0$
#385
1$
#390
0&
0$
