lab6/regfile.v
module RegisterFile #(
  parameter DataWidth  = 32,
  parameter NumRegs    = 32,
  parameter IndexWidth = $clog2(NumRegs)
) (
  input  clk,
  input  writeEn,
  input  [IndexWidth-1:0] writeAddr,
  input  [ DataWidth-1:0] writeData,
  input  [IndexWidth-1:0] readAddr1,
  input  [IndexWidth-1:0] readAddr2,
  output [ DataWidth-1:0] readData1,
  output [ DataWidth-1:0] readData2
);

  logic [DataWidth-1:0] regs[NumRegs];

  always_ff @(posedge clk) begin
    if (writeEn) begin
      regs[writeAddr] <= writeData;
    end
  end

  assign readData1 = regs[readAddr1];
  assign readData2 = regs[readAddr2];

endmodule

lab6/regfile_tb.v
`timescale 1ns/1ps
`include "regfile.v"
module regfile_tb;
  localparam DataWidth = 32;
  localparam NumRegs =32;
  localparam IndexWidth = $clog2(NumRegs);

  reg clk;
  reg writeEn;
  reg [IndexWidth-1:0] writeAddr;
  reg [DataWidth-1:0] writeData;
  reg [IndexWidth-1:0] readAddr1;
  reg [IndexWidth-1:0] readAddr2;
  wire [DataWidth-1:0] readData1;
  wire [DataWidth-1:0] readData2;

  RegisterFile #(
    .DataWidth(DataWidth),
    .NumRegs(NumRegs),
    .IndexWidth(IndexWidth)
  ) dut (
    .clk(clk),
    .writeEn(writeEn),
    .writeAddr(writeAddr),
    .writeData(writeData),
    .readAddr1(readAddr1),
    .readAddr2(readAddr2),
    .readData1(readData1),
    .readData2(readData2)
  );

  initial begin
    $dumpfile("wave_regfile.vcd");
    $dumpvars(0);
  end

  initial begin
    clk = 1'b0;
    forever #5 clk = ~clk;
  end

  initial begin
    writeEn = 1'b0;
    writeAddr = '0;
    writeData = '0;
    readAddr1 = '0;
    readAddr2 = '0;

    @(negedge clk);
    writeEn = 1'b1;
    writeAddr = 0;
    writeData = 32'h11111111;
    @(negedge clk);
    writeEn = 1'b0;

    @(negedge clk);
    writeEn = 1'b1;
    writeAddr = 1;
    writeData = 32'h22222222;
    @(negedge clk);
    writeEn = 1'b0;

    @(negedge clk);
    writeEn = 1'b1;
    writeAddr = 3;
    writeData = 32'h000000A5;
    @(negedge clk);
    writeEn = 1'b0;

    @(negedge clk);
    writeEn = 1'b1;
    writeAddr = 5;
    writeData = 32'h12345678;
    @(negedge clk);
    writeEn = 1'b0;

    @(negedge clk);
    readAddr1 = 3;
    readAddr2 = 5;
    #2;
    readAddr1 = 5;
    #2;
    readAddr2 = 3;


    @(negedge clk);
    writeEn = 1'b1;
    writeAddr = 3;
    writeData = 32'h0F0F0F0F;
    @(negedge clk);
    writeEn = 1'b0;
    @(negedge clk);
    readAddr1 = 3;
    readAddr2 = 5;

    #10;
    $finish;
  end
endmodule

lab6/wave_regfile.vcd
$date
	Wed May 27 19:11:38 2026
$end
$version
	Icarus Verilog
$end
$timescale
	1ps
$end
$scope module regfile_tb $end
$var wire 32 ! readData2 [31:0] $end
$var wire 32 " readData1 [31:0] $end
$var reg 1 # clk $end
$var reg 5 $ readAddr1 [4:0] $end
$var reg 5 % readAddr2 [4:0] $end
$var reg 5 & writeAddr [4:0] $end
$var reg 32 ' writeData [31:0] $end
$var reg 1 ( writeEn $end
$scope module dut $end
$var wire 1 # clk $end
$var wire 5 ) readAddr1 [4:0] $end
$var wire 5 * readAddr2 [4:0] $end
$var wire 32 + readData1 [31:0] $end
$var wire 32 , readData2 [31:0] $end
$var wire 5 - writeAddr [4:0] $end
$var wire 32 . writeData [31:0] $end
$var wire 1 ( writeEn $end
$upscope $end
$upscope $end
$enddefinitions $end
#0
$dumpvars
b0 .
b0 -
bx ,
bx +
b0 *
b0 )
0(
b0 '
b0 &
b0 %
b0 $
0#
bx "
bx !
$end
#5000
1#
#10000
b10001000100010001000100010001 '
b10001000100010001000100010001 .
1(
0#
#15000
b10001000100010001000100010001 "
b10001000100010001000100010001 +
b10001000100010001000100010001 !
b10001000100010001000100010001 ,
1#
#20000
0(
0#
#25000
1#
#30000
b100010001000100010001000100010 '
b100010001000100010001000100010 .
b1 &
b1 -
1(
0#
#35000
1#
#40000
0(
0#
#45000
1#
#50000
b10100101 '
b10100101 .
b11 &
b11 -
1(
0#
#55000
1#
#60000
0(
0#
#65000
1#
#70000
b10010001101000101011001111000 '
b10010001101000101011001111000 .
b101 &
b101 -
1(
0#
#75000
1#
#80000
0(
0#
#85000
1#
#90000
b10010001101000101011001111000 !
b10010001101000101011001111000 ,
b101 %
b101 *
b10100101 "
b10100101 +
b11 $
b11 )
0#
#92000
b10010001101000101011001111000 "
b10010001101000101011001111000 +
b101 $
b101 )
#94000
b10100101 !
b10100101 ,
b11 %
b11 *
#95000
1#
#100000
b1111000011110000111100001111 '
b1111000011110000111100001111 .
b11 &
b11 -
1(
0#
#105000
b1111000011110000111100001111 !
b1111000011110000111100001111 ,
1#
#110000
0(
0#
#115000
1#
#120000
b10010001101000101011001111000 !
b10010001101000101011001111000 ,
b101 %
b101 *
b1111000011110000111100001111 "
b1111000011110000111100001111 +
b11 $
b11 )
0#
